{
"meta":{"test_sets":[],"test_metrics":[],"learn_metrics":[{"best_value":"Min","name":"RMSE"}],"launch_mode":"Train","parameters":"","iteration_count":1000,"learn_sets":["learn"],"name":"experiment"},
"iterations":[
{"learn":[14.61268541],"iteration":0,"passed_time":0.1511646066,"remaining_time":151.013442},
{"learn":[14.23196558],"iteration":1,"passed_time":0.1525623898,"remaining_time":76.12863249},
{"learn":[13.86674177],"iteration":2,"passed_time":0.1538967375,"remaining_time":51.14501577},
{"learn":[13.49946468],"iteration":3,"passed_time":0.1551941164,"remaining_time":38.64333499},
{"learn":[13.16661202],"iteration":4,"passed_time":0.1565862048,"remaining_time":31.16065476},
{"learn":[12.85632158],"iteration":5,"passed_time":0.1578976877,"remaining_time":26.15838359},
{"learn":[12.56784336],"iteration":6,"passed_time":0.1592657688,"remaining_time":22.59298691},
{"learn":[12.31617801],"iteration":7,"passed_time":0.1605683836,"remaining_time":19.91047957},
{"learn":[12.01509946],"iteration":8,"passed_time":0.1619614419,"remaining_time":17.83375432},
{"learn":[11.71512571],"iteration":9,"passed_time":0.1635686908,"remaining_time":16.19330039},
{"learn":[11.43264457],"iteration":10,"passed_time":0.1649590782,"remaining_time":14.83132075},
{"learn":[11.17973129],"iteration":11,"passed_time":0.1664768836,"remaining_time":13.70659675},
{"learn":[10.93746433],"iteration":12,"passed_time":0.1679525869,"remaining_time":12.75147718},
{"learn":[10.69387075],"iteration":13,"passed_time":0.1693607723,"remaining_time":11.92783725},
{"learn":[10.4615922],"iteration":14,"passed_time":0.1708480325,"remaining_time":11.2190208},
{"learn":[10.2299235],"iteration":15,"passed_time":0.1721128619,"remaining_time":10.58494101},
{"learn":[10.01419731],"iteration":16,"passed_time":0.1733991972,"remaining_time":10.02655358},
{"learn":[9.795856918],"iteration":17,"passed_time":0.174697478,"remaining_time":9.530717967},
{"learn":[9.60040151],"iteration":18,"passed_time":0.1759481672,"remaining_time":9.084481688},
{"learn":[9.418664989],"iteration":19,"passed_time":0.1772302134,"remaining_time":8.684280456},
{"learn":[9.249278645],"iteration":20,"passed_time":0.1784975181,"remaining_time":8.321384296},
{"learn":[9.090113396],"iteration":21,"passed_time":0.1797930731,"remaining_time":7.992619339},
{"learn":[8.909548708],"iteration":22,"passed_time":0.1810696175,"remaining_time":7.691522447},
{"learn":[8.740140208],"iteration":23,"passed_time":0.1823542993,"remaining_time":7.415741503},
{"learn":[8.59377682],"iteration":24,"passed_time":0.1836258731,"remaining_time":7.161409049},
{"learn":[8.453885414],"iteration":25,"passed_time":0.1850837719,"remaining_time":6.93352284},
{"learn":[8.317732234],"iteration":26,"passed_time":0.1863948038,"remaining_time":6.717116449},
{"learn":[8.180896085],"iteration":27,"passed_time":0.1878450337,"remaining_time":6.52090617},
{"learn":[8.053220863],"iteration":28,"passed_time":0.1892097803,"remaining_time":6.335265402},
{"learn":[7.924234474],"iteration":29,"passed_time":0.190576447,"remaining_time":6.161971787},
{"learn":[7.818879511],"iteration":30,"passed_time":0.1919935915,"remaining_time":6.00134807},
{"learn":[7.719346395],"iteration":31,"passed_time":0.1934386242,"remaining_time":5.851518382},
{"learn":[7.624163594],"iteration":32,"passed_time":0.1948806291,"remaining_time":5.710592981},
{"learn":[7.524952543],"iteration":33,"passed_time":0.1963766859,"remaining_time":5.579408195},
{"learn":[7.424464745],"iteration":34,"passed_time":0.1976726217,"remaining_time":5.450116571},
{"learn":[7.327482321],"iteration":35,"passed_time":0.1990141997,"remaining_time":5.329158015},
{"learn":[7.238666841],"iteration":36,"passed_time":0.2004089115,"remaining_time":5.216048157},
{"learn":[7.158842395],"iteration":37,"passed_time":0.2017481484,"remaining_time":5.107413653},
{"learn":[7.074348246],"iteration":38,"passed_time":0.203124546,"remaining_time":5.005197145},
{"learn":[6.992269093],"iteration":39,"passed_time":0.2044503956,"remaining_time":4.906809494},
{"learn":[6.925219745],"iteration":40,"passed_time":0.2058966195,"remaining_time":4.81597215},
{"learn":[6.86013671],"iteration":41,"passed_time":0.2072707849,"remaining_time":4.727747903},
{"learn":[6.786739622],"iteration":42,"passed_time":0.2087572386,"remaining_time":4.646062264},
{"learn":[6.73057926],"iteration":43,"passed_time":0.2103214308,"remaining_time":4.569711088},
{"learn":[6.666356486],"iteration":44,"passed_time":0.2116947666,"remaining_time":4.49263338},
{"learn":[6.606182832],"iteration":45,"passed_time":0.2132677149,"remaining_time":4.422986957},
{"learn":[6.547854615],"iteration":46,"passed_time":0.2147933496,"remaining_time":4.355277919},
{"learn":[6.49240675],"iteration":47,"passed_time":0.2160916618,"remaining_time":4.285817959},
{"learn":[6.431317261],"iteration":48,"passed_time":0.2177883328,"remaining_time":4.226871521},
{"learn":[6.377586395],"iteration":49,"passed_time":0.2191455555,"remaining_time":4.163765555},
{"learn":[6.327558015],"iteration":50,"passed_time":0.2206120453,"remaining_time":4.105114333},
{"learn":[6.282040317],"iteration":51,"passed_time":0.2220627453,"remaining_time":4.048374665},
{"learn":[6.237655841],"iteration":52,"passed_time":0.2235459081,"remaining_time":3.994301414},
{"learn":[6.192792003],"iteration":53,"passed_time":0.224981488,"remaining_time":3.941342364},
{"learn":[6.150579347],"iteration":54,"passed_time":0.2263544782,"remaining_time":3.88918149},
{"learn":[6.115693845],"iteration":55,"passed_time":0.2276466299,"remaining_time":3.837471761},
{"learn":[6.078780782],"iteration":56,"passed_time":0.2289088537,"remaining_time":3.787035948},
{"learn":[6.045146957],"iteration":57,"passed_time":0.2301962774,"remaining_time":3.738705058},
{"learn":[6.008080327],"iteration":58,"passed_time":0.2314561863,"remaining_time":3.691530023},
{"learn":[5.977575734],"iteration":59,"passed_time":0.2326507057,"remaining_time":3.644861056},
{"learn":[5.948036502],"iteration":60,"passed_time":0.23392719,"remaining_time":3.600944777},
{"learn":[5.914888282],"iteration":61,"passed_time":0.2354618954,"remaining_time":3.56231061},
{"learn":[5.884957796],"iteration":62,"passed_time":0.2367633128,"remaining_time":3.52138451},
{"learn":[5.849539885],"iteration":63,"passed_time":0.2380431242,"remaining_time":3.481380692},
{"learn":[5.821387627],"iteration":64,"passed_time":0.2393556816,"remaining_time":3.44303942},
{"learn":[5.797012279],"iteration":65,"passed_time":0.2404967469,"remaining_time":3.403393357},
{"learn":[5.768685095],"iteration":66,"passed_time":0.2417875831,"remaining_time":3.366982314},
{"learn":[5.755484587],"iteration":67,"passed_time":0.242521319,"remaining_time":3.323968667},
{"learn":[5.731887055],"iteration":68,"passed_time":0.2438091802,"remaining_time":3.289657199},
{"learn":[5.707148487],"iteration":69,"passed_time":0.2451189416,"remaining_time":3.256580224},
{"learn":[5.685365039],"iteration":70,"passed_time":0.246440462,"remaining_time":3.22455196},
{"learn":[5.663541834],"iteration":71,"passed_time":0.2476771953,"remaining_time":3.192283851},
{"learn":[5.638108797],"iteration":72,"passed_time":0.2489822619,"remaining_time":3.161733655},
{"learn":[5.619204893],"iteration":73,"passed_time":0.2504462363,"remaining_time":3.133962363},
{"learn":[5.598472793],"iteration":74,"passed_time":0.2518551981,"remaining_time":3.10621411},
{"learn":[5.577007075],"iteration":75,"passed_time":0.2531400856,"remaining_time":3.077650514},
{"learn":[5.562637084],"iteration":76,"passed_time":0.2608605814,"remaining_time":3.126939177},
{"learn":[5.54729991],"iteration":77,"passed_time":0.2621616882,"remaining_time":3.098885597},
{"learn":[5.530737623],"iteration":78,"passed_time":0.2633313946,"remaining_time":3.069977398},
{"learn":[5.513704873],"iteration":79,"passed_time":0.2644661164,"remaining_time":3.041360338},
{"learn":[5.501575529],"iteration":80,"passed_time":0.2657516099,"remaining_time":3.015132463},
{"learn":[5.484080734],"iteration":81,"passed_time":0.2670162903,"remaining_time":2.989279933},
{"learn":[5.472178894],"iteration":82,"passed_time":0.2682323656,"remaining_time":2.963482883},
{"learn":[5.458923342],"iteration":83,"passed_time":0.2693605534,"remaining_time":2.937312702},
{"learn":[5.451382371],"iteration":84,"passed_time":0.270167706,"remaining_time":2.908275895},
{"learn":[5.441410748],"iteration":85,"passed_time":0.2712611697,"remaining_time":2.882938478},
{"learn":[5.434047468],"iteration":86,"passed_time":0.2720139764,"remaining_time":2.854583453},
{"learn":[5.422107497],"iteration":87,"passed_time":0.2731749141,"remaining_time":2.831085473},
{"learn":[5.40731265],"iteration":88,"passed_time":0.2744145497,"remaining_time":2.808894997},
{"learn":[5.396360181],"iteration":89,"passed_time":0.2756369586,"remaining_time":2.786995914},
{"learn":[5.383793239],"iteration":90,"passed_time":0.276802937,"remaining_time":2.76498758},
{"learn":[5.369605034],"iteration":91,"passed_time":0.2780222332,"remaining_time":2.743958562},
{"learn":[5.357467333],"iteration":92,"passed_time":0.2792951398,"remaining_time":2.723878406},
{"learn":[5.341109968],"iteration":93,"passed_time":0.2808134062,"remaining_time":2.706563255},
{"learn":[5.330529276],"iteration":94,"passed_time":0.2822615908,"remaining_time":2.688913049},
{"learn":[5.319862075],"iteration":95,"passed_time":0.2837870905,"remaining_time":2.672328435},
{"learn":[5.313052243],"iteration":96,"passed_time":0.284977962,"remaining_time":2.652939172},
{"learn":[5.299677207],"iteration":97,"passed_time":0.2862022649,"remaining_time":2.63422901},
{"learn":[5.287546698],"iteration":98,"passed_time":0.2875294535,"remaining_time":2.616808461},
{"learn":[5.279803754],"iteration":99,"passed_time":0.2888110086,"remaining_time":2.599299078},
{"learn":[5.272254612],"iteration":100,"passed_time":0.2901321168,"remaining_time":2.582463099},
{"learn":[5.268813888],"iteration":101,"passed_time":0.290919709,"remaining_time":2.561234301},
{"learn":[5.258113767],"iteration":102,"passed_time":0.2921008999,"remaining_time":2.543830167},
{"learn":[5.251018576],"iteration":103,"passed_time":0.2932917114,"remaining_time":2.526820898},
{"learn":[5.24171237],"iteration":104,"passed_time":0.2946922892,"remaining_time":2.511900941},
{"learn":[5.233984943],"iteration":105,"passed_time":0.2960292626,"remaining_time":2.49669963},
{"learn":[5.226240449],"iteration":106,"passed_time":0.29739908,"remaining_time":2.482031574},
{"learn":[5.220541644],"iteration":107,"passed_time":0.2986489949,"remaining_time":2.466619477},
{"learn":[5.211712096],"iteration":108,"passed_time":0.2998896327,"remaining_time":2.451391401},
{"learn":[5.203388597],"iteration":109,"passed_time":0.3011544159,"remaining_time":2.436613002},
{"learn":[5.196026544],"iteration":110,"passed_time":0.3025573749,"remaining_time":2.423184742},
{"learn":[5.188716772],"iteration":111,"passed_time":0.3038574709,"remaining_time":2.409155662},
{"learn":[5.182163132],"iteration":112,"passed_time":0.3051641923,"remaining_time":2.395403881},
{"learn":[5.17764747],"iteration":113,"passed_time":0.3064477717,"remaining_time":2.381690577},
{"learn":[5.170548056],"iteration":114,"passed_time":0.3077001346,"remaining_time":2.367953209},
{"learn":[5.165901827],"iteration":115,"passed_time":0.3087533223,"remaining_time":2.352913249},
{"learn":[5.160333668],"iteration":116,"passed_time":0.3101707421,"remaining_time":2.340861242},
{"learn":[5.148953243],"iteration":117,"passed_time":0.3115549803,"remaining_time":2.328741463},
{"learn":[5.144729126],"iteration":118,"passed_time":0.3126820156,"remaining_time":2.314897948},
{"learn":[5.139939946],"iteration":119,"passed_time":0.3142003975,"remaining_time":2.304136248},
{"learn":[5.132898872],"iteration":120,"passed_time":0.3154238886,"remaining_time":2.291385108},
{"learn":[5.129073077],"iteration":121,"passed_time":0.3167490869,"remaining_time":2.279554904},
{"learn":[5.127123916],"iteration":122,"passed_time":0.3175237249,"remaining_time":2.263969974},
{"learn":[5.121282057],"iteration":123,"passed_time":0.318749362,"remaining_time":2.251810009},
{"learn":[5.114489821],"iteration":124,"passed_time":0.3200270789,"remaining_time":2.240189552},
{"learn":[5.107777291],"iteration":125,"passed_time":0.3213206684,"remaining_time":2.228843366},
{"learn":[5.103518754],"iteration":126,"passed_time":0.3226594556,"remaining_time":2.217966179},
{"learn":[5.101133351],"iteration":127,"passed_time":0.3237197437,"remaining_time":2.205340754},
{"learn":[5.096462705],"iteration":128,"passed_time":0.3252562076,"remaining_time":2.196109743},
{"learn":[5.08562082],"iteration":129,"passed_time":0.3266983694,"remaining_time":2.186366011},
{"learn":[5.080483682],"iteration":130,"passed_time":0.3280094275,"remaining_time":2.175879332},
{"learn":[5.07437499],"iteration":131,"passed_time":0.3292843057,"remaining_time":2.165293768},
{"learn":[5.070683732],"iteration":132,"passed_time":0.3306009296,"remaining_time":2.155120346},
{"learn":[5.06432037],"iteration":133,"passed_time":0.3320293342,"remaining_time":2.145801518},
{"learn":[5.057436484],"iteration":134,"passed_time":0.3333611365,"remaining_time":2.135980616},
{"learn":[5.053254656],"iteration":135,"passed_time":0.3347611985,"remaining_time":2.126718202},
{"learn":[5.04801663],"iteration":136,"passed_time":0.3361074878,"remaining_time":2.117231839},
{"learn":[5.045680836],"iteration":137,"passed_time":0.3372061665,"remaining_time":2.106316779},
{"learn":[5.041857933],"iteration":138,"passed_time":0.3385660789,"remaining_time":2.097161107},
{"learn":[5.035264888],"iteration":139,"passed_time":0.340099722,"remaining_time":2.089184006},
{"learn":[5.028771948],"iteration":140,"passed_time":0.3414351682,"remaining_time":2.080090847},
{"learn":[5.024912247],"iteration":141,"passed_time":0.3429525392,"remaining_time":2.072206187},
{"learn":[5.02239068],"iteration":142,"passed_time":0.3442492266,"remaining_time":2.063088022},
{"learn":[5.017110572],"iteration":143,"passed_time":0.3457026298,"remaining_time":2.055010077},
{"learn":[5.010707886],"iteration":144,"passed_time":0.3471475736,"remaining_time":2.046973623},
{"learn":[5.004389868],"iteration":145,"passed_time":0.3484506245,"remaining_time":2.038197489},
{"learn":[4.997628683],"iteration":146,"passed_time":0.3497927838,"remaining_time":2.029749963},
{"learn":[4.991497851],"iteration":147,"passed_time":0.3510891644,"remaining_time":2.02113492},
{"learn":[4.988345253],"iteration":148,"passed_time":0.3523497021,"remaining_time":2.012413399},
{"learn":[4.98460423],"iteration":149,"passed_time":0.3535915712,"remaining_time":2.00368557},
{"learn":[4.982441783],"iteration":150,"passed_time":0.3550314381,"remaining_time":1.996170138},
{"learn":[4.977461771],"iteration":151,"passed_time":0.3564453957,"remaining_time":1.988590103},
{"learn":[4.973601586],"iteration":152,"passed_time":0.3578296862,"remaining_time":1.980926433},
{"learn":[4.968328804],"iteration":153,"passed_time":0.3592156341,"remaining_time":1.973353418},
{"learn":[4.9640736],"iteration":154,"passed_time":0.3606144307,"remaining_time":1.965930284},
{"learn":[4.960865882],"iteration":155,"passed_time":0.3619362958,"remaining_time":1.958168164},
{"learn":[4.957014156],"iteration":156,"passed_time":0.3632677861,"remaining_time":1.950539769},
{"learn":[4.952244852],"iteration":157,"passed_time":0.3645644535,"remaining_time":1.942805505},
{"learn":[4.949695675],"iteration":158,"passed_time":0.3659297347,"remaining_time":1.935515137},
{"learn":[4.946584698],"iteration":159,"passed_time":0.367243268,"remaining_time":1.928027157},
{"learn":[4.940192834],"iteration":160,"passed_time":0.3685364379,"remaining_time":1.92050976},
{"learn":[4.936727994],"iteration":161,"passed_time":0.3698881567,"remaining_time":1.91337207},
{"learn":[4.932342063],"iteration":162,"passed_time":0.3712990265,"remaining_time":1.906609111},
{"learn":[4.925830838],"iteration":163,"passed_time":0.3726989742,"remaining_time":1.899855747},
{"learn":[4.922571773],"iteration":164,"passed_time":0.3743042101,"remaining_time":1.894206154},
{"learn":[4.918395814],"iteration":165,"passed_time":0.3756986462,"remaining_time":1.88754621},
{"learn":[4.911142452],"iteration":166,"passed_time":0.3769973579,"remaining_time":1.880471851},
{"learn":[4.908276131],"iteration":167,"passed_time":0.3784089143,"remaining_time":1.8740251},
{"learn":[4.904584645],"iteration":168,"passed_time":0.3797525581,"remaining_time":1.867303998},
{"learn":[4.89795517],"iteration":169,"passed_time":0.3811063473,"remaining_time":1.860695696},
{"learn":[4.895556491],"iteration":170,"passed_time":0.3824274168,"remaining_time":1.853990225},
{"learn":[4.890591233],"iteration":171,"passed_time":0.3837367712,"remaining_time":1.847290968},
{"learn":[4.884629277],"iteration":172,"passed_time":0.3853863718,"remaining_time":1.842280517},
{"learn":[4.880550786],"iteration":173,"passed_time":0.3869559163,"remaining_time":1.83692866},
{"learn":[4.876384842],"iteration":174,"passed_time":0.3885976239,"remaining_time":1.831960227},
{"learn":[4.872638238],"iteration":175,"passed_time":0.3899115782,"remaining_time":1.825495116},
{"learn":[4.869137118],"iteration":176,"passed_time":0.3911694027,"remaining_time":1.818827223},
{"learn":[4.863587157],"iteration":177,"passed_time":0.3924199215,"remaining_time":1.812186379},
{"learn":[4.858028614],"iteration":178,"passed_time":0.3936820966,"remaining_time":1.805659225},
{"learn":[4.853838176],"iteration":179,"passed_time":0.3949795818,"remaining_time":1.799351428},
{"learn":[4.853462329],"iteration":180,"passed_time":0.395690489,"remaining_time":1.790444809},
{"learn":[4.851573196],"iteration":181,"passed_time":0.3970444011,"remaining_time":1.784518242},
{"learn":[4.848442087],"iteration":182,"passed_time":0.3984191412,"remaining_time":1.778734636},
{"learn":[4.845547104],"iteration":183,"passed_time":0.3999657093,"remaining_time":1.773760972},
{"learn":[4.839868817],"iteration":184,"passed_time":0.4015144485,"remaining_time":1.768833922},
{"learn":[4.836336958],"iteration":185,"passed_time":0.4027538624,"remaining_time":1.762589484},
{"learn":[4.831124789],"iteration":186,"passed_time":0.4040427004,"remaining_time":1.756613452},
{"learn":[4.827407333],"iteration":187,"passed_time":0.4053756077,"remaining_time":1.750877625},
{"learn":[4.824088918],"iteration":188,"passed_time":0.4066959757,"remaining_time":1.745134583},
{"learn":[4.820934539],"iteration":189,"passed_time":0.4079460536,"remaining_time":1.739138439},
{"learn":[4.816975227],"iteration":190,"passed_time":0.4092067642,"remaining_time":1.733237027},
{"learn":[4.812340486],"iteration":191,"passed_time":0.410549872,"remaining_time":1.727730711},
{"learn":[4.806402747],"iteration":192,"passed_time":0.4117937467,"remaining_time":1.721852609},
{"learn":[4.801521788],"iteration":193,"passed_time":0.413001364,"remaining_time":1.715871646},
{"learn":[4.797601172],"iteration":194,"passed_time":0.414341003,"remaining_time":1.710484654},
{"learn":[4.792694629],"iteration":195,"passed_time":0.4156649286,"remaining_time":1.705074503},
{"learn":[4.789794613],"iteration":196,"passed_time":0.4169997962,"remaining_time":1.699750438},
{"learn":[4.785367055],"iteration":197,"passed_time":0.4182418269,"remaining_time":1.694090632},
{"learn":[4.780376856],"iteration":198,"passed_time":0.4195397631,"remaining_time":1.688700252},
{"learn":[4.776691261],"iteration":199,"passed_time":0.420907496,"remaining_time":1.683629984},
{"learn":[4.773470753],"iteration":200,"passed_time":0.4221737184,"remaining_time":1.67819304},
{"learn":[4.77207327],"iteration":201,"passed_time":0.4234011493,"remaining_time":1.672644144},
{"learn":[4.767347177],"iteration":202,"passed_time":0.4247006326,"remaining_time":1.66742071},
{"learn":[4.763983068],"iteration":203,"passed_time":0.4259140022,"remaining_time":1.661899734},
{"learn":[4.761588849],"iteration":204,"passed_time":0.4271828201,"remaining_time":1.656635815},
{"learn":[4.758558086],"iteration":205,"passed_time":0.4285550074,"remaining_time":1.651809106},
{"learn":[4.753678804],"iteration":206,"passed_time":0.4300274011,"remaining_time":1.647399657},
{"learn":[4.746510889],"iteration":207,"passed_time":0.4314591955,"remaining_time":1.64286386},
{"learn":[4.744840601],"iteration":208,"passed_time":0.4328540424,"remaining_time":1.638217931},
{"learn":[4.741702222],"iteration":209,"passed_time":0.4340712301,"remaining_time":1.632934628},
{"learn":[4.739352853],"iteration":210,"passed_time":0.4354048677,"remaining_time":1.628125311},
{"learn":[4.735539287],"iteration":211,"passed_time":0.4366204219,"remaining_time":1.62290987},
{"learn":[4.730726751],"iteration":212,"passed_time":0.4378110979,"remaining_time":1.617640066},
{"learn":[4.726416092],"iteration":213,"passed_time":0.4392023571,"remaining_time":1.613145106},
{"learn":[4.721293082],"iteration":214,"passed_time":0.4404340658,"remaining_time":1.608096473},
{"learn":[4.718443695],"iteration":215,"passed_time":0.4417315188,"remaining_time":1.603321809},
{"learn":[4.711627962],"iteration":216,"passed_time":0.4429592891,"remaining_time":1.598327757},
{"learn":[4.709790764],"iteration":217,"passed_time":0.444355068,"remaining_time":1.593970932},
{"learn":[4.706913073],"iteration":218,"passed_time":0.4459138661,"remaining_time":1.590222509},
{"learn":[4.703846389],"iteration":219,"passed_time":0.4472819306,"remaining_time":1.585817754},
{"learn":[4.701001135],"iteration":220,"passed_time":0.4486404539,"remaining_time":1.581406849},
{"learn":[4.700380864],"iteration":221,"passed_time":0.4499245217,"remaining_time":1.576762513},
{"learn":[4.695837486],"iteration":222,"passed_time":0.4512049971,"remaining_time":1.572135797},
{"learn":[4.691242996],"iteration":223,"passed_time":0.452370705,"remaining_time":1.567141371},
{"learn":[4.690284609],"iteration":224,"passed_time":0.4536116935,"remaining_time":1.562440278},
{"learn":[4.68827119],"iteration":225,"passed_time":0.454770657,"remaining_time":1.557488887},
{"learn":[4.686922425],"iteration":226,"passed_time":0.4559386197,"remaining_time":1.552601555},
{"learn":[4.686085874],"iteration":227,"passed_time":0.4571960245,"remaining_time":1.548049697},
{"learn":[4.683230741],"iteration":228,"passed_time":0.458650754,"remaining_time":1.544190967},
{"learn":[4.6773487],"iteration":229,"passed_time":0.4600868842,"remaining_time":1.540290873},
{"learn":[4.671462906],"iteration":230,"passed_time":0.4613169695,"remaining_time":1.535726188},
{"learn":[4.664799601],"iteration":231,"passed_time":0.4626119432,"remaining_time":1.531405053},
{"learn":[4.660979386],"iteration":232,"passed_time":0.4638499515,"remaining_time":1.526922373},
{"learn":[4.656281279],"iteration":233,"passed_time":0.4651135509,"remaining_time":1.522551196},
{"learn":[4.651997094],"iteration":234,"passed_time":0.4664360333,"remaining_time":1.518398151},
{"learn":[4.650151977],"iteration":235,"passed_time":0.4677595754,"remaining_time":1.514272524},
{"learn":[4.648478046],"iteration":236,"passed_time":0.469012472,"remaining_time":1.509943106},
{"learn":[4.646364602],"iteration":237,"passed_time":0.470357703,"remaining_time":1.505935167},
{"learn":[4.642635873],"iteration":238,"passed_time":0.4716723548,"remaining_time":1.501852142},
{"learn":[4.640860821],"iteration":239,"passed_time":0.4728201945,"remaining_time":1.497263949},
{"learn":[4.639446822],"iteration":240,"passed_time":0.4741323763,"remaining_time":1.493221882},
{"learn":[4.637120072],"iteration":241,"passed_time":0.4756229514,"remaining_time":1.489761145},
{"learn":[4.633769267],"iteration":242,"passed_time":0.4770400959,"remaining_time":1.486087871},
{"learn":[4.630491517],"iteration":243,"passed_time":0.4783519204,"remaining_time":1.48210677},
{"learn":[4.627813333],"iteration":244,"passed_time":0.4798853683,"remaining_time":1.478830421},
{"learn":[4.622496304],"iteration":245,"passed_time":0.4812933933,"remaining_time":1.475183815},
{"learn":[4.618979301],"iteration":246,"passed_time":0.4828946168,"remaining_time":1.472144317},
{"learn":[4.616563458],"iteration":247,"passed_time":0.4845237362,"remaining_time":1.469201007},
{"learn":[4.614759385],"iteration":248,"passed_time":0.4859803362,"remaining_time":1.465747922},
{"learn":[4.61251363],"iteration":249,"passed_time":0.4875767633,"remaining_time":1.46273029},
{"learn":[4.608796693],"iteration":250,"passed_time":0.4890208501,"remaining_time":1.459269389},
{"learn":[4.60847774],"iteration":251,"passed_time":0.4902257054,"remaining_time":1.455114395},
{"learn":[4.605195659],"iteration":252,"passed_time":0.4915429628,"remaining_time":1.451314598},
{"learn":[4.60103766],"iteration":253,"passed_time":0.4935612703,"remaining_time":1.449593337},
{"learn":[4.599325598],"iteration":254,"passed_time":0.494821069,"remaining_time":1.445653711},
{"learn":[4.597012808],"iteration":255,"passed_time":0.4961977872,"remaining_time":1.442074819},
{"learn":[4.594161533],"iteration":256,"passed_time":0.4973649982,"remaining_time":1.437907368},
{"learn":[4.592197259],"iteration":257,"passed_time":0.4985210655,"remaining_time":1.433731126},
{"learn":[4.58952828],"iteration":258,"passed_time":0.5000567778,"remaining_time":1.430664372},
{"learn":[4.585816572],"iteration":259,"passed_time":0.5012750531,"remaining_time":1.42670592},
{"learn":[4.582934052],"iteration":260,"passed_time":0.5025150595,"remaining_time":1.422829996},
{"learn":[4.582234842],"iteration":261,"passed_time":0.503845489,"remaining_time":1.419228896},
{"learn":[4.57571562],"iteration":262,"passed_time":0.5051164676,"remaining_time":1.415478466},
{"learn":[4.571197349],"iteration":263,"passed_time":0.506437086,"remaining_time":1.41188521},
{"learn":[4.56723703],"iteration":264,"passed_time":0.5078239097,"remaining_time":1.408492731},
{"learn":[4.560335567],"iteration":265,"passed_time":0.5092341957,"remaining_time":1.405180074},
{"learn":[4.554709345],"iteration":266,"passed_time":0.5105556272,"remaining_time":1.401637733},
{"learn":[4.552806306],"iteration":267,"passed_time":0.5119098574,"remaining_time":1.398201551},
{"learn":[4.550766241],"iteration":268,"passed_time":0.5134366846,"remaining_time":1.395249875},
{"learn":[4.549216045],"iteration":269,"passed_time":0.5147725469,"remaining_time":1.391792442},
{"learn":[4.547687452],"iteration":270,"passed_time":0.5162845826,"remaining_time":1.388824578},
{"learn":[4.545642435],"iteration":271,"passed_time":0.5176010923,"remaining_time":1.3853441},
{"learn":[4.543930359],"iteration":272,"passed_time":0.5193162681,"remaining_time":1.382941124},
{"learn":[4.541029943],"iteration":273,"passed_time":0.5208834288,"remaining_time":1.380150983},
{"learn":[4.537781449],"iteration":274,"passed_time":0.5224291116,"remaining_time":1.377313112},
{"learn":[4.53066128],"iteration":275,"passed_time":0.5237441481,"remaining_time":1.373879577},
{"learn":[4.526763956],"iteration":276,"passed_time":0.5250423788,"remaining_time":1.370417472},
{"learn":[4.522036004],"iteration":277,"passed_time":0.5262434822,"remaining_time":1.366718684},
{"learn":[4.515307629],"iteration":278,"passed_time":0.5275583484,"remaining_time":1.363331789},
{"learn":[4.51109143],"iteration":279,"passed_time":0.5289924691,"remaining_time":1.360266349},
{"learn":[4.508233494],"iteration":280,"passed_time":0.5302526373,"remaining_time":1.356767424},
{"learn":[4.502555629],"iteration":281,"passed_time":0.5315637629,"remaining_time":1.35341412},
{"learn":[4.500081355],"iteration":282,"passed_time":0.5327361149,"remaining_time":1.349723655},
{"learn":[4.495281743],"iteration":283,"passed_time":0.5340817006,"remaining_time":1.346487668},
{"learn":[4.492138869],"iteration":284,"passed_time":0.535459095,"remaining_time":1.343344747},
{"learn":[4.491708261],"iteration":285,"passed_time":0.5367785711,"remaining_time":1.34006958},
{"learn":[4.489398865],"iteration":286,"passed_time":0.5380140918,"remaining_time":1.336599469},
{"learn":[4.485796373],"iteration":287,"passed_time":0.539259119,"remaining_time":1.333168377},
{"learn":[4.479542205],"iteration":288,"passed_time":0.5405796185,"remaining_time":1.329938093},
{"learn":[4.475986993],"iteration":289,"passed_time":0.5418364709,"remaining_time":1.326565153},
{"learn":[4.468661855],"iteration":290,"passed_time":0.543187469,"remaining_time":1.323436136},
{"learn":[4.463785664],"iteration":291,"passed_time":0.544605701,"remaining_time":1.320482316},
{"learn":[4.460445831],"iteration":292,"passed_time":0.5457790251,"remaining_time":1.316948023},
{"learn":[4.45692492],"iteration":293,"passed_time":0.5470402669,"remaining_time":1.313640913},
{"learn":[4.454031688],"iteration":294,"passed_time":0.5483175816,"remaining_time":1.310386085},
{"learn":[4.451672391],"iteration":295,"passed_time":0.5497169856,"remaining_time":1.307434993},
{"learn":[4.45031553],"iteration":296,"passed_time":0.5509512899,"remaining_time":1.304103558},
{"learn":[4.446782666],"iteration":297,"passed_time":0.55234359,"remaining_time":1.30115839},
{"learn":[4.444369689],"iteration":298,"passed_time":0.5536503088,"remaining_time":1.298022965},
{"learn":[4.44411683],"iteration":299,"passed_time":0.5548746858,"remaining_time":1.2947076},
{"learn":[4.440876943],"iteration":300,"passed_time":0.5562813741,"remaining_time":1.291829503},
{"learn":[4.439336453],"iteration":301,"passed_time":0.5574586767,"remaining_time":1.288430981},
{"learn":[4.436666901],"iteration":302,"passed_time":0.5587314082,"remaining_time":1.285266639},
{"learn":[4.433043336],"iteration":303,"passed_time":0.5600595013,"remaining_time":1.28224149},
{"learn":[4.431419305],"iteration":304,"passed_time":0.5612827319,"remaining_time":1.27898852},
{"learn":[4.428859646],"iteration":305,"passed_time":0.5625870857,"remaining_time":1.275932802},
{"learn":[4.424552441],"iteration":306,"passed_time":0.5640055229,"remaining_time":1.273146018},
{"learn":[4.422706391],"iteration":307,"passed_time":0.5654727003,"remaining_time":1.270477625},
{"learn":[4.421427994],"iteration":308,"passed_time":0.5669865664,"remaining_time":1.267921415},
{"learn":[4.418733158],"iteration":309,"passed_time":0.5684071883,"remaining_time":1.265164387},
{"learn":[4.415656941],"iteration":310,"passed_time":0.5697236379,"remaining_time":1.262185166},
{"learn":[4.410747417],"iteration":311,"passed_time":0.5711216803,"remaining_time":1.259396526},
{"learn":[4.408126521],"iteration":312,"passed_time":0.5723506192,"remaining_time":1.256245608},
{"learn":[4.407843853],"iteration":313,"passed_time":0.5734607785,"remaining_time":1.252847433},
{"learn":[4.405219398],"iteration":314,"passed_time":0.5748653614,"remaining_time":1.25010404},
{"learn":[4.402708465],"iteration":315,"passed_time":0.5761824811,"remaining_time":1.247179801},
{"learn":[4.40104971],"iteration":316,"passed_time":0.5775159831,"remaining_time":1.244300998},
{"learn":[4.400830038],"iteration":317,"passed_time":0.5787802313,"remaining_time":1.241283389},
{"learn":[4.39784288],"iteration":318,"passed_time":0.5802142257,"remaining_time":1.238639146},
{"learn":[4.393741845],"iteration":319,"passed_time":0.5815060139,"remaining_time":1.23570028},
{"learn":[4.393425936],"iteration":320,"passed_time":0.5832009312,"remaining_time":1.2336244},
{"learn":[4.390505974],"iteration":321,"passed_time":0.5844234102,"remaining_time":1.230556125},
{"learn":[4.390305136],"iteration":322,"passed_time":0.5855805097,"remaining_time":1.227362245},
{"learn":[4.38568203],"iteration":323,"passed_time":0.5868615176,"remaining_time":1.224439463},
{"learn":[4.383057135],"iteration":324,"passed_time":0.588088867,"remaining_time":1.221415339},
{"learn":[4.380662684],"iteration":325,"passed_time":0.5894645042,"remaining_time":1.218708822},
{"learn":[4.37805727],"iteration":326,"passed_time":0.5906585525,"remaining_time":1.215636715},
{"learn":[4.373708319],"iteration":327,"passed_time":0.5920050563,"remaining_time":1.212888408},
{"learn":[4.36887921],"iteration":328,"passed_time":0.5932223743,"remaining_time":1.209885146},
{"learn":[4.367895929],"iteration":329,"passed_time":0.5945930897,"remaining_time":1.207204152},
{"learn":[4.362140573],"iteration":330,"passed_time":0.5960323701,"remaining_time":1.204669654},
{"learn":[4.361931924],"iteration":331,"passed_time":0.5974237195,"remaining_time":1.202045315},
{"learn":[4.359656377],"iteration":332,"passed_time":0.5986767537,"remaining_time":1.199151336},
{"learn":[4.354281355],"iteration":333,"passed_time":0.5999033315,"remaining_time":1.196214428},
{"learn":[4.348589447],"iteration":334,"passed_time":0.6012996027,"remaining_time":1.193624585},
{"learn":[4.346355698],"iteration":335,"passed_time":0.602572756,"remaining_time":1.190798542},
{"learn":[4.343894047],"iteration":336,"passed_time":0.6038502664,"remaining_time":1.187990287},
{"learn":[4.341561356],"iteration":337,"passed_time":0.6052201801,"remaining_time":1.185372069},
{"learn":[4.338869061],"iteration":338,"passed_time":0.6063838397,"remaining_time":1.18235905},
{"learn":[4.333720063],"iteration":339,"passed_time":0.607559148,"remaining_time":1.179379523},
{"learn":[4.330892223],"iteration":340,"passed_time":0.6089742682,"remaining_time":1.176874026},
{"learn":[4.328311474],"iteration":341,"passed_time":0.6103159041,"remaining_time":1.174233523},
{"learn":[4.324580133],"iteration":342,"passed_time":0.611735936,"remaining_time":1.171750758},
{"learn":[4.323354432],"iteration":343,"passed_time":0.6132908707,"remaining_time":1.169531428},
{"learn":[4.323159553],"iteration":344,"passed_time":0.6146036363,"remaining_time":1.166856179},
{"learn":[4.318639682],"iteration":345,"passed_time":0.6161419041,"remaining_time":1.164615044},
{"learn":[4.312712208],"iteration":346,"passed_time":0.6174890291,"remaining_time":1.162018259},
{"learn":[4.311461062],"iteration":347,"passed_time":0.6188691498,"remaining_time":1.159490476},
{"learn":[4.311178356],"iteration":348,"passed_time":0.6201351918,"remaining_time":1.156756475},
{"learn":[4.311102505],"iteration":349,"passed_time":0.6212991259,"remaining_time":1.153841234},
{"learn":[4.310232308],"iteration":350,"passed_time":0.6226374809,"remaining_time":1.151258476},
{"learn":[4.305128197],"iteration":351,"passed_time":0.6240665308,"remaining_time":1.14884975},
{"learn":[4.304595496],"iteration":352,"passed_time":0.6254089257,"remaining_time":1.146287748},
{"learn":[4.3004992],"iteration":353,"passed_time":0.6267492863,"remaining_time":1.143728924},
{"learn":[4.297581524],"iteration":354,"passed_time":0.6280234317,"remaining_time":1.141056658},
{"learn":[4.297355825],"iteration":355,"passed_time":0.6293631061,"remaining_time":1.138510787},
{"learn":[4.295758715],"iteration":356,"passed_time":0.6305771371,"remaining_time":1.135745376},
{"learn":[4.292500657],"iteration":357,"passed_time":0.631816452,"remaining_time":1.133033973},
{"learn":[4.290797586],"iteration":358,"passed_time":0.6329764377,"remaining_time":1.130189127},
{"learn":[4.286410608],"iteration":359,"passed_time":0.6343301368,"remaining_time":1.127698021},
{"learn":[4.280278245],"iteration":360,"passed_time":0.6356025685,"remaining_time":1.125069366},
{"learn":[4.279941283],"iteration":361,"passed_time":0.6368534381,"remaining_time":1.122410203},
{"learn":[4.274426275],"iteration":362,"passed_time":0.6381564329,"remaining_time":1.119850269},
{"learn":[4.273567658],"iteration":363,"passed_time":0.6393941745,"remaining_time":1.117183228},
{"learn":[4.269488271],"iteration":364,"passed_time":0.6407880693,"remaining_time":1.114795682},
{"learn":[4.266838205],"iteration":365,"passed_time":0.6420955545,"remaining_time":1.112263884},
{"learn":[4.263456509],"iteration":366,"passed_time":0.6434611189,"remaining_time":1.109838933},
{"learn":[4.260360204],"iteration":367,"passed_time":0.644786122,"remaining_time":1.107350079},
{"learn":[4.255120549],"iteration":368,"passed_time":0.6460421374,"remaining_time":1.104749563},
{"learn":[4.252582211],"iteration":369,"passed_time":0.6472209031,"remaining_time":1.102024781},
{"learn":[4.247857931],"iteration":370,"passed_time":0.6485070432,"remaining_time":1.099490378},
{"learn":[4.245288911],"iteration":371,"passed_time":0.6498295117,"remaining_time":1.097024014},
{"learn":[4.24048515],"iteration":372,"passed_time":0.6511158008,"remaining_time":1.094502968},
{"learn":[4.2378365],"iteration":373,"passed_time":0.6523608729,"remaining_time":1.091919536},
{"learn":[4.236751063],"iteration":374,"passed_time":0.6537744637,"remaining_time":1.089624106},
{"learn":[4.233240093],"iteration":375,"passed_time":0.6550777351,"remaining_time":1.087150284},
{"learn":[4.230358421],"iteration":376,"passed_time":0.656372288,"remaining_time":1.084668264},
{"learn":[4.225853583],"iteration":377,"passed_time":0.6576160999,"remaining_time":1.082109032},
{"learn":[4.224702126],"iteration":378,"passed_time":0.6589017677,"remaining_time":1.079625324},
{"learn":[4.224361982],"iteration":379,"passed_time":0.6602028593,"remaining_time":1.077173086},
{"learn":[4.223787954],"iteration":380,"passed_time":0.6613637721,"remaining_time":1.074499147},
{"learn":[4.22144054],"iteration":381,"passed_time":0.6625608469,"remaining_time":1.071891632},
{"learn":[4.217739335],"iteration":382,"passed_time":0.6638875785,"remaining_time":1.069500355},
{"learn":[4.215611665],"iteration":383,"passed_time":0.6651133545,"remaining_time":1.066952673},
{"learn":[4.210236863],"iteration":384,"passed_time":0.6664426001,"remaining_time":1.06457714},
{"learn":[4.208454294],"iteration":385,"passed_time":0.6676232699,"remaining_time":1.061970694},
{"learn":[4.207446501],"iteration":386,"passed_time":0.6689534588,"remaining_time":1.05960845},
{"learn":[4.204985442],"iteration":387,"passed_time":0.6701832835,"remaining_time":1.05709322},
{"learn":[4.202796622],"iteration":388,"passed_time":0.6714769457,"remaining_time":1.054684869},
{"learn":[4.199774004],"iteration":389,"passed_time":0.6727980801,"remaining_time":1.052325202},
{"learn":[4.199458358],"iteration":390,"passed_time":0.6739807803,"remaining_time":1.049755231},
{"learn":[4.19751254],"iteration":391,"passed_time":0.6751884978,"remaining_time":1.047231139},
{"learn":[4.195201346],"iteration":392,"passed_time":0.6766729473,"remaining_time":1.045141168},
{"learn":[4.190593508],"iteration":393,"passed_time":0.6779345938,"remaining_time":1.042711583},
{"learn":[4.187212054],"iteration":394,"passed_time":0.6791211161,"remaining_time":1.040172849},
{"learn":[4.184984466],"iteration":395,"passed_time":0.6803603408,"remaining_time":1.037721328},
{"learn":[4.182832144],"iteration":396,"passed_time":0.6817391736,"remaining_time":1.035487964},
{"learn":[4.179752812],"iteration":397,"passed_time":0.6829991726,"remaining_time":1.033079151},
{"learn":[4.17878934],"iteration":398,"passed_time":0.6842232551,"remaining_time":1.030621996},
{"learn":[4.174548229],"iteration":399,"passed_time":0.6856494236,"remaining_time":1.028474135},
{"learn":[4.168872556],"iteration":400,"passed_time":0.6868626729,"remaining_time":1.026011823},
{"learn":[4.163926494],"iteration":401,"passed_time":0.6880453069,"remaining_time":1.023510183},
{"learn":[4.159485076],"iteration":402,"passed_time":0.6893828655,"remaining_time":1.021244592},
{"learn":[4.155926102],"iteration":403,"passed_time":0.6908327311,"remaining_time":1.019149277},
{"learn":[4.153540115],"iteration":404,"passed_time":0.6922050299,"remaining_time":1.016943192},
{"learn":[4.150983044],"iteration":405,"passed_time":0.6934563404,"remaining_time":1.014564202},
{"learn":[4.146539132],"iteration":406,"passed_time":0.6947150067,"remaining_time":1.012201472},
{"learn":[4.144869174],"iteration":407,"passed_time":0.6961016948,"remaining_time":1.01002991},
{"learn":[4.142825962],"iteration":408,"passed_time":0.6973280822,"remaining_time":1.007630554},
{"learn":[4.142467378],"iteration":409,"passed_time":0.6985180593,"remaining_time":1.005184524},
{"learn":[4.141800768],"iteration":410,"passed_time":0.6998566687,"remaining_time":1.00295761},
{"learn":[4.140107084],"iteration":411,"passed_time":0.7010529017,"remaining_time":1.000531811},
{"learn":[4.136243196],"iteration":412,"passed_time":0.7022557262,"remaining_time":0.9981213348},
{"learn":[4.133618439],"iteration":413,"passed_time":0.7034250217,"remaining_time":0.9956692337},
{"learn":[4.131053025],"iteration":414,"passed_time":0.7047077393,"remaining_time":0.9933831988},
{"learn":[4.128379975],"iteration":415,"passed_time":0.7059637198,"remaining_time":0.9910644529},
{"learn":[4.127068571],"iteration":416,"passed_time":0.7071279546,"remaining_time":0.988622536},
{"learn":[4.125969877],"iteration":417,"passed_time":0.708385813,"remaining_time":0.9863170889},
{"learn":[4.123893633],"iteration":418,"passed_time":0.7097225446,"remaining_time":0.9841260105},
{"learn":[4.119643722],"iteration":419,"passed_time":0.711002376,"remaining_time":0.981860424},
{"learn":[4.11465686],"iteration":420,"passed_time":0.7121831761,"remaining_time":0.9794633229},
{"learn":[4.111565986],"iteration":421,"passed_time":0.7135093224,"remaining_time":0.9772710625},
{"learn":[4.106322452],"iteration":422,"passed_time":0.7148160512,"remaining_time":0.9750564103},
{"learn":[4.104222175],"iteration":423,"passed_time":0.7161008572,"remaining_time":0.9728162588},
{"learn":[4.103008002],"iteration":424,"passed_time":0.7173556452,"remaining_time":0.9705399905},
{"learn":[4.099176337],"iteration":425,"passed_time":0.7186880488,"remaining_time":0.9683730986},
{"learn":[4.096525716],"iteration":426,"passed_time":0.7199351303,"remaining_time":0.9660956199},
{"learn":[4.094967724],"iteration":427,"passed_time":0.7211920428,"remaining_time":0.9638360946},
{"learn":[4.094683584],"iteration":428,"passed_time":0.7223795572,"remaining_time":0.9614888746},
{"learn":[4.091096563],"iteration":429,"passed_time":0.7236872481,"remaining_time":0.9593063522},
{"learn":[4.089178677],"iteration":430,"passed_time":0.7249688207,"remaining_time":0.9570934083},
{"learn":[4.085335077],"iteration":431,"passed_time":0.7261978336,"remaining_time":0.9548156701},
{"learn":[4.084852122],"iteration":432,"passed_time":0.727462643,"remaining_time":0.9525896503},
{"learn":[4.080322952],"iteration":433,"passed_time":0.7287545428,"remaining_time":0.9504033899},
{"learn":[4.077449519],"iteration":434,"passed_time":0.7300738559,"remaining_time":0.9482568473},
{"learn":[4.076568374],"iteration":435,"passed_time":0.7314227046,"remaining_time":0.9461523059},
{"learn":[4.076071793],"iteration":436,"passed_time":0.7327244166,"remaining_time":0.9439904956},
{"learn":[4.075027644],"iteration":437,"passed_time":0.7340713099,"remaining_time":0.9418905848},
{"learn":[4.07020837],"iteration":438,"passed_time":0.7353895594,"remaining_time":0.9397575007},
{"learn":[4.06833694],"iteration":439,"passed_time":0.7367872563,"remaining_time":0.9377292352},
{"learn":[4.063936568],"iteration":440,"passed_time":0.7381338602,"remaining_time":0.9356390654},
{"learn":[4.061734926],"iteration":441,"passed_time":0.7394637746,"remaining_time":0.9335311906},
{"learn":[4.060815619],"iteration":442,"passed_time":0.7407868021,"remaining_time":0.9314181688},
{"learn":[4.056407489],"iteration":443,"passed_time":0.742109024,"remaining_time":0.9293076967},
{"learn":[4.05238936],"iteration":444,"passed_time":0.7433737332,"remaining_time":0.927129038},
{"learn":[4.049685254],"iteration":445,"passed_time":0.7446526086,"remaining_time":0.9249720744},
{"learn":[4.045162016],"iteration":446,"passed_time":0.7459041096,"remaining_time":0.9227851736},
{"learn":[4.042955482],"iteration":447,"passed_time":0.7473236204,"remaining_time":0.9208094609},
{"learn":[4.041467663],"iteration":448,"passed_time":0.7486652877,"remaining_time":0.9187406983},
{"learn":[4.038920476],"iteration":449,"passed_time":0.7500098774,"remaining_time":0.916678739},
{"learn":[4.036694383],"iteration":450,"passed_time":0.7514456216,"remaining_time":0.9147309229},
{"learn":[4.034999007],"iteration":451,"passed_time":0.7528194597,"remaining_time":0.9127103184},
{"learn":[4.031928018],"iteration":452,"passed_time":0.7541302311,"remaining_time":0.9106164159},
{"learn":[4.028718143],"iteration":453,"passed_time":0.7554751,"remaining_time":0.9085669705},
{"learn":[4.027401978],"iteration":454,"passed_time":0.7568693857,"remaining_time":0.9065798136},
{"learn":[4.025930598],"iteration":455,"passed_time":0.7582464146,"remaining_time":0.90457467},
{"learn":[4.021074523],"iteration":456,"passed_time":0.7596628575,"remaining_time":0.9026191064},
{"learn":[4.020268486],"iteration":457,"passed_time":0.7608990406,"remaining_time":0.9004525764},
{"learn":[4.017986361],"iteration":458,"passed_time":0.7622667509,"remaining_time":0.8984451247},
{"learn":[4.014814804],"iteration":459,"passed_time":0.7635137422,"remaining_time":0.8962987409},
{"learn":[4.009704796],"iteration":460,"passed_time":0.7646935301,"remaining_time":0.8940776849},
{"learn":[4.008440457],"iteration":461,"passed_time":0.7658511808,"remaining_time":0.8918353577},
{"learn":[4.004854849],"iteration":462,"passed_time":0.7670621252,"remaining_time":0.8896595275},
{"learn":[4.000898028],"iteration":463,"passed_time":0.7683986075,"remaining_time":0.8876328742},
{"learn":[3.996617985],"iteration":464,"passed_time":0.7697432399,"remaining_time":0.8856185663},
{"learn":[3.995443319],"iteration":465,"passed_time":0.771100236,"remaining_time":0.8836213004},
{"learn":[3.990771995],"iteration":466,"passed_time":0.7723851757,"remaining_time":0.8815445367},
{"learn":[3.989249359],"iteration":467,"passed_time":0.7737224297,"remaining_time":0.8795306252},
{"learn":[3.986599538],"iteration":468,"passed_time":0.7749791017,"remaining_time":0.8774283646},
{"learn":[3.985628919],"iteration":469,"passed_time":0.7762029436,"remaining_time":0.8752926811},
{"learn":[3.985086112],"iteration":470,"passed_time":0.7773951005,"remaining_time":0.8731252827},
{"learn":[3.98466839],"iteration":471,"passed_time":0.7785758304,"remaining_time":0.870949234},
{"learn":[3.984233894],"iteration":472,"passed_time":0.7798310393,"remaining_time":0.8688603757},
{"learn":[3.981855845],"iteration":473,"passed_time":0.7816547628,"remaining_time":0.8674059182},
{"learn":[3.978684264],"iteration":474,"passed_time":0.7831224639,"remaining_time":0.8655564075},
{"learn":[3.974361269],"iteration":475,"passed_time":0.7844754214,"remaining_time":0.8635821866},
{"learn":[3.972074049],"iteration":476,"passed_time":0.7856477133,"remaining_time":0.8614124823},
{"learn":[3.97191982],"iteration":477,"passed_time":0.7869378428,"remaining_time":0.8593756359},
{"learn":[3.969616848],"iteration":478,"passed_time":0.7883658505,"remaining_time":0.8574918749},
{"learn":[3.968533527],"iteration":479,"passed_time":0.7895891512,"remaining_time":0.8553882472},
{"learn":[3.967568753],"iteration":480,"passed_time":0.7910216899,"remaining_time":0.8535140479},
{"learn":[3.966232553],"iteration":481,"passed_time":0.7922674085,"remaining_time":0.8514409079},
{"learn":[3.961522393],"iteration":482,"passed_time":0.7936694107,"remaining_time":0.8495384789},
{"learn":[3.955829553],"iteration":483,"passed_time":0.7950348173,"remaining_time":0.8475991028},
{"learn":[3.954248095],"iteration":484,"passed_time":0.7962482671,"remaining_time":0.8455007372},
{"learn":[3.951922606],"iteration":485,"passed_time":0.7976276209,"remaining_time":0.8435814756},
{"learn":[3.94978202],"iteration":486,"passed_time":0.7988811462,"remaining_time":0.841531885},
{"learn":[3.949518999],"iteration":487,"passed_time":0.8001723833,"remaining_time":0.8395251234},
{"learn":[3.945431216],"iteration":488,"passed_time":0.8014772041,"remaining_time":0.8375354832},
{"learn":[3.943249086],"iteration":489,"passed_time":0.8028432883,"remaining_time":0.8356124021},
{"learn":[3.941981548],"iteration":490,"passed_time":0.8041979534,"remaining_time":0.8336797521},
{"learn":[3.936600517],"iteration":491,"passed_time":0.8054378095,"remaining_time":0.831630909},
{"learn":[3.934476885],"iteration":492,"passed_time":0.8068256087,"remaining_time":0.8297374921},
{"learn":[3.93045798],"iteration":493,"passed_time":0.8081184078,"remaining_time":0.8277488145},
{"learn":[3.925977375],"iteration":494,"passed_time":0.8094629761,"remaining_time":0.8258157635},
{"learn":[3.92457993],"iteration":495,"passed_time":0.8107798967,"remaining_time":0.8238569918},
{"learn":[3.919849146],"iteration":496,"passed_time":0.8120931433,"remaining_time":0.8218970847},
{"learn":[3.919681964],"iteration":497,"passed_time":0.8134069673,"remaining_time":0.8199403566},
{"learn":[3.917633027],"iteration":498,"passed_time":0.8147947103,"remaining_time":0.8180604206},
{"learn":[3.916616419],"iteration":499,"passed_time":0.8161037441,"remaining_time":0.8161037441},
{"learn":[3.912896166],"iteration":500,"passed_time":0.817344591,"remaining_time":0.8140817383},
{"learn":[3.912769674],"iteration":501,"passed_time":0.8185352896,"remaining_time":0.8120130961},
{"learn":[3.909373788],"iteration":502,"passed_time":0.8199146073,"remaining_time":0.8101343137},
{"learn":[3.906706036],"iteration":503,"passed_time":0.8212805773,"remaining_time":0.8082443777},
{"learn":[3.903895664],"iteration":504,"passed_time":0.8225289115,"remaining_time":0.8062412103},
{"learn":[3.902982967],"iteration":505,"passed_time":0.8236840668,"remaining_time":0.8041500574},
{"learn":[3.900905528],"iteration":506,"passed_time":0.8249983958,"remaining_time":0.802217375},
{"learn":[3.897463465],"iteration":507,"passed_time":0.8263076474,"remaining_time":0.8002822097},
{"learn":[3.895918033],"iteration":508,"passed_time":0.8275976231,"remaining_time":0.7983309095},
{"learn":[3.893921936],"iteration":509,"passed_time":0.828847562,"remaining_time":0.7963437361},
{"learn":[3.890237934],"iteration":510,"passed_time":0.8300728318,"remaining_time":0.794335841},
{"learn":[3.887311613],"iteration":511,"passed_time":0.8313697096,"remaining_time":0.7923992545},
{"learn":[3.884869735],"iteration":512,"passed_time":0.8327895437,"remaining_time":0.7905818865},
{"learn":[3.882101231],"iteration":513,"passed_time":0.8341471124,"remaining_time":0.7887071919},
{"learn":[3.88060368],"iteration":514,"passed_time":0.8354358929,"remaining_time":0.7867697244},
{"learn":[3.877726076],"iteration":515,"passed_time":0.8367049675,"remaining_time":0.7848162873},
{"learn":[3.874938145],"iteration":516,"passed_time":0.8381362308,"remaining_time":0.7830170202},
{"learn":[3.874340833],"iteration":517,"passed_time":0.8393156278,"remaining_time":0.780984812},
{"learn":[3.873105224],"iteration":518,"passed_time":0.8405786033,"remaining_time":0.7790333491},
{"learn":[3.869800236],"iteration":519,"passed_time":0.8419471192,"remaining_time":0.7771819562},
{"learn":[3.867932518],"iteration":520,"passed_time":0.8432722673,"remaining_time":0.7752925452},
{"learn":[3.866666962],"iteration":521,"passed_time":0.8446200237,"remaining_time":0.7734259987},
{"learn":[3.865527652],"iteration":522,"passed_time":0.8459433881,"remaining_time":0.7715391895},
{"learn":[3.861900081],"iteration":523,"passed_time":0.847152258,"remaining_time":0.7695505245},
{"learn":[3.858502887],"iteration":524,"passed_time":0.8484767047,"remaining_time":0.7676693995},
{"learn":[3.858335097],"iteration":525,"passed_time":0.8497804371,"remaining_time":0.7657717247},
{"learn":[3.855719306],"iteration":526,"passed_time":0.8511626318,"remaining_time":0.7639467265},
{"learn":[3.855137428],"iteration":527,"passed_time":0.8524669803,"remaining_time":0.7620538158},
{"learn":[3.851985706],"iteration":528,"passed_time":0.8537680972,"remaining_time":0.7601602529},
{"learn":[3.851051809],"iteration":529,"passed_time":0.8549592193,"remaining_time":0.7581713831},
{"learn":[3.850679146],"iteration":530,"passed_time":0.8561406908,"remaining_time":0.7561769943},
{"learn":[3.848179484],"iteration":531,"passed_time":0.857427928,"remaining_time":0.7542787036},
{"learn":[3.844551071],"iteration":532,"passed_time":0.8587907017,"remaining_time":0.7524488887},
{"learn":[3.841604794],"iteration":533,"passed_time":0.8602486432,"remaining_time":0.7507038722},
{"learn":[3.83969656],"iteration":534,"passed_time":0.8615629142,"remaining_time":0.7488350563},
{"learn":[3.836811463],"iteration":535,"passed_time":0.86297191,"remaining_time":0.7470503102},
{"learn":[3.834182551],"iteration":536,"passed_time":0.8642366445,"remaining_time":0.7451425817},
{"learn":[3.828012842],"iteration":537,"passed_time":0.8655907631,"remaining_time":0.743314001},
{"learn":[3.826636176],"iteration":538,"passed_time":0.8669497835,"remaining_time":0.7414913733},
{"learn":[3.826189798],"iteration":539,"passed_time":0.8688178177,"remaining_time":0.7401040669},
{"learn":[3.824104738],"iteration":540,"passed_time":0.8701660238,"remaining_time":0.7382739462},
{"learn":[3.82300218],"iteration":541,"passed_time":0.8714306227,"remaining_time":0.7363749542},
{"learn":[3.817146402],"iteration":542,"passed_time":0.8726507667,"remaining_time":0.7344408847},
{"learn":[3.814638044],"iteration":543,"passed_time":0.8741101527,"remaining_time":0.7327099809},
{"learn":[3.812979573],"iteration":544,"passed_time":0.8754027714,"remaining_time":0.7308408458},
{"learn":[3.811938825],"iteration":545,"passed_time":0.8766104828,"remaining_time":0.728903222},
{"learn":[3.811479418],"iteration":546,"passed_time":0.8778221888,"remaining_time":0.726971575},
{"learn":[3.80742981],"iteration":547,"passed_time":0.8790154917,"remaining_time":0.7250273763},
{"learn":[3.805097043],"iteration":548,"passed_time":0.8803713854,"remaining_time":0.7232194806},
{"learn":[3.801577232],"iteration":549,"passed_time":0.8817663351,"remaining_time":0.7214451833},
{"learn":[3.799762083],"iteration":550,"passed_time":0.8829812681,"remaining_time":0.7195255705},
{"learn":[3.796393455],"iteration":551,"passed_time":0.8842704155,"remaining_time":0.717668743},
{"learn":[3.793486459],"iteration":552,"passed_time":0.8854894772,"remaining_time":0.715757317},
{"learn":[3.792006091],"iteration":553,"passed_time":0.8866556861,"remaining_time":0.7138058412},
{"learn":[3.78932128],"iteration":554,"passed_time":0.8878146796,"remaining_time":0.7118514098},
{"learn":[3.787581812],"iteration":555,"passed_time":0.8892011787,"remaining_time":0.7100815168},
{"learn":[3.785308865],"iteration":556,"passed_time":0.8904089263,"remaining_time":0.7081708337},
{"learn":[3.78465475],"iteration":557,"passed_time":0.8916760859,"remaining_time":0.7063097311},
{"learn":[3.780498869],"iteration":558,"passed_time":0.8929481468,"remaining_time":0.7044546203},
{"learn":[3.778734909],"iteration":559,"passed_time":0.8943351457,"remaining_time":0.7026919002},
{"learn":[3.778652349],"iteration":560,"passed_time":0.8955566165,"remaining_time":0.7008009886},
{"learn":[3.777928006],"iteration":561,"passed_time":0.896726403,"remaining_time":0.6988721789},
{"learn":[3.776131406],"iteration":562,"passed_time":0.8981164898,"remaining_time":0.6971170622},
{"learn":[3.772925617],"iteration":563,"passed_time":0.8993679005,"remaining_time":0.6952560366},
{"learn":[3.7727745],"iteration":564,"passed_time":0.9006339987,"remaining_time":0.6934084769},
{"learn":[3.771763073],"iteration":565,"passed_time":0.9020370945,"remaining_time":0.6916680195},
{"learn":[3.768738162],"iteration":566,"passed_time":0.9034415846,"remaining_time":0.6899298168},
{"learn":[3.767220794],"iteration":567,"passed_time":0.904801968,"remaining_time":0.6881592432},
{"learn":[3.766691102],"iteration":568,"passed_time":0.9060497283,"remaining_time":0.686304803},
{"learn":[3.766259335],"iteration":569,"passed_time":0.9072549906,"remaining_time":0.6844204315},
{"learn":[3.76116362],"iteration":570,"passed_time":0.9086506431,"remaining_time":0.6826814814},
{"learn":[3.758633056],"iteration":571,"passed_time":0.9099702996,"remaining_time":0.6808868675},
{"learn":[3.754603809],"iteration":572,"passed_time":0.9112473851,"remaining_time":0.6790621875},
{"learn":[3.754070549],"iteration":573,"passed_time":0.9125512378,"remaining_time":0.677259281},
{"learn":[3.750534319],"iteration":574,"passed_time":0.9137605988,"remaining_time":0.6753882687},
{"learn":[3.746491516],"iteration":575,"passed_time":0.9150251838,"remaining_time":0.6735602047},
{"learn":[3.744210544],"iteration":576,"passed_time":0.916354591,"remaining_time":0.6717816153},
{"learn":[3.742929991],"iteration":577,"passed_time":0.917589236,"remaining_time":0.6699353938},
{"learn":[3.740402992],"iteration":578,"passed_time":0.9188814639,"remaining_time":0.6681331542},
{"learn":[3.739644243],"iteration":579,"passed_time":0.9201333657,"remaining_time":0.6663034717},
{"learn":[3.737529404],"iteration":580,"passed_time":0.9212957766,"remaining_time":0.6644112399},
{"learn":[3.737196923],"iteration":581,"passed_time":0.9224711651,"remaining_time":0.6625308368},
{"learn":[3.733954464],"iteration":582,"passed_time":0.92366891,"remaining_time":0.660668843},
{"learn":[3.731608623],"iteration":583,"passed_time":0.9250616276,"remaining_time":0.6589480087},
{"learn":[3.729843952],"iteration":584,"passed_time":0.9263397301,"remaining_time":0.657146988},
{"learn":[3.727223798],"iteration":585,"passed_time":0.9275734544,"remaining_time":0.6553163995},
{"learn":[3.725351667],"iteration":586,"passed_time":0.9289444029,"remaining_time":0.6535843925},
{"learn":[3.725026912],"iteration":587,"passed_time":0.9302680853,"remaining_time":0.6518204952},
{"learn":[3.721974565],"iteration":588,"passed_time":0.931518504,"remaining_time":0.6500069697},
{"learn":[3.720269493],"iteration":589,"passed_time":0.9327229345,"remaining_time":0.6481633951},
{"learn":[3.718907466],"iteration":590,"passed_time":0.933915199,"remaining_time":0.6463135641},
{"learn":[3.715602912],"iteration":591,"passed_time":0.9351542233,"remaining_time":0.644498181},
{"learn":[3.714463059],"iteration":592,"passed_time":0.9365756108,"remaining_time":0.6428099049},
{"learn":[3.710802077],"iteration":593,"passed_time":0.937939296,"remaining_time":0.6410830878},
{"learn":[3.708032435],"iteration":594,"passed_time":0.9391764964,"remaining_time":0.6392713967},
{"learn":[3.703788939],"iteration":595,"passed_time":0.9406533383,"remaining_time":0.637624075},
{"learn":[3.702500944],"iteration":596,"passed_time":0.9419829359,"remaining_time":0.6358779283},
{"learn":[3.698196925],"iteration":597,"passed_time":0.9432553315,"remaining_time":0.6340947212},
{"learn":[3.69658891],"iteration":598,"passed_time":0.9446891215,"remaining_time":0.632421265},
{"learn":[3.696124066],"iteration":599,"passed_time":0.945990563,"remaining_time":0.6306603753},
{"learn":[3.693537052],"iteration":600,"passed_time":0.9473071903,"remaining_time":0.6289110964},
{"learn":[3.691343275],"iteration":601,"passed_time":0.9485439298,"remaining_time":0.6271104386},
{"learn":[3.690973831],"iteration":602,"passed_time":0.94979796,"remaining_time":0.625323035},
{"learn":[3.686151073],"iteration":603,"passed_time":0.9511916292,"remaining_time":0.6236289489},
{"learn":[3.683921982],"iteration":604,"passed_time":0.9523401905,"remaining_time":0.6217758268},
{"learn":[3.679975271],"iteration":605,"passed_time":0.9536320515,"remaining_time":0.6200181985},
{"learn":[3.674047638],"iteration":606,"passed_time":0.9549790763,"remaining_time":0.6182978204},
{"learn":[3.673151794],"iteration":607,"passed_time":0.9562945098,"remaining_time":0.6165583024},
{"learn":[3.670953108],"iteration":608,"passed_time":0.9575165117,"remaining_time":0.6147601906},
{"learn":[3.6703947],"iteration":609,"passed_time":0.958760687,"remaining_time":0.6129781442},
{"learn":[3.668433805],"iteration":610,"passed_time":0.9600547789,"remaining_time":0.6112296383},
{"learn":[3.668304956],"iteration":611,"passed_time":0.9613342971,"remaining_time":0.6094733779},
{"learn":[3.667880012],"iteration":612,"passed_time":0.9625231443,"remaining_time":0.6076614304},
{"learn":[3.667282264],"iteration":613,"passed_time":0.9639114298,"remaining_time":0.6059768923},
{"learn":[3.664611483],"iteration":614,"passed_time":0.9652970683,"remaining_time":0.6042916607},
{"learn":[3.662543394],"iteration":615,"passed_time":0.9666157875,"remaining_time":0.6025656857},
{"learn":[3.659041959],"iteration":616,"passed_time":0.9679392159,"remaining_time":0.6008439541},
{"learn":[3.656868545],"iteration":617,"passed_time":0.9693178582,"remaining_time":0.5991576405},
{"learn":[3.654785614],"iteration":618,"passed_time":0.9707675021,"remaining_time":0.5975160231},
{"learn":[3.654566096],"iteration":619,"passed_time":0.972088599,"remaining_time":0.5957962381},
{"learn":[3.651007045],"iteration":620,"passed_time":0.9735109885,"remaining_time":0.5941395566},
{"learn":[3.648921786],"iteration":621,"passed_time":0.9749406158,"remaining_time":0.5924880269},
{"learn":[3.647655706],"iteration":622,"passed_time":0.9762578596,"remaining_time":0.5907692024},
{"learn":[3.647241144],"iteration":623,"passed_time":0.977607931,"remaining_time":0.5890714456},
{"learn":[3.644195689],"iteration":624,"passed_time":0.9788778212,"remaining_time":0.5873266927},
{"learn":[3.642632246],"iteration":625,"passed_time":0.9802234631,"remaining_time":0.5856287143},
{"learn":[3.642523322],"iteration":626,"passed_time":0.9812227157,"remaining_time":0.5837257942},
{"learn":[3.641494659],"iteration":627,"passed_time":0.9824790631,"remaining_time":0.5819780437},
{"learn":[3.63976496],"iteration":628,"passed_time":0.9839097103,"remaining_time":0.5803346622},
{"learn":[3.637945652],"iteration":629,"passed_time":0.985346057,"remaining_time":0.5786953033},
{"learn":[3.636233667],"iteration":630,"passed_time":0.9866144941,"remaining_time":0.5769583967},
{"learn":[3.635304404],"iteration":631,"passed_time":0.9877879773,"remaining_time":0.575167683},
{"learn":[3.632234951],"iteration":632,"passed_time":0.9890695638,"remaining_time":0.5734415954},
{"learn":[3.631630987],"iteration":633,"passed_time":0.9903342829,"remaining_time":0.5717071728},
{"learn":[3.630301009],"iteration":634,"passed_time":0.9919332041,"remaining_time":0.5701663299},
{"learn":[3.629077964],"iteration":635,"passed_time":0.9932481317,"remaining_time":0.5684627672},
{"learn":[3.628004522],"iteration":636,"passed_time":0.994530719,"remaining_time":0.5667419953},
{"learn":[3.625062876],"iteration":637,"passed_time":0.9958513336,"remaining_time":0.5650441736},
{"learn":[3.624917986],"iteration":638,"passed_time":0.9970956278,"remaining_time":0.5633044157},
{"learn":[3.622887087],"iteration":639,"passed_time":0.9983910839,"remaining_time":0.5615949847},
{"learn":[3.621220865],"iteration":640,"passed_time":0.9998088184,"remaining_time":0.5599553288},
{"learn":[3.621143844],"iteration":641,"passed_time":1.001024017,"remaining_time":0.5582034238},
{"learn":[3.620822821],"iteration":642,"passed_time":1.002260336,"remaining_time":0.5564649142},
{"learn":[3.619202826],"iteration":643,"passed_time":1.003530987,"remaining_time":0.5547469434},
{"learn":[3.618204882],"iteration":644,"passed_time":1.004728784,"remaining_time":0.5529902608},
{"learn":[3.614259666],"iteration":645,"passed_time":1.005971606,"remaining_time":0.5512599824},
{"learn":[3.613415661],"iteration":646,"passed_time":1.00728521,"remaining_time":0.5495698285},
{"learn":[3.611096773],"iteration":647,"passed_time":1.008542423,"remaining_time":0.547850205},
{"learn":[3.610820695],"iteration":648,"passed_time":1.009824197,"remaining_time":0.54614529},
{"learn":[3.609290065],"iteration":649,"passed_time":1.011033819,"remaining_time":0.5444028255},
{"learn":[3.60897947],"iteration":650,"passed_time":1.012301552,"remaining_time":0.5426931514},
{"learn":[3.606570702],"iteration":651,"passed_time":1.013873697,"remaining_time":0.5411473107},
{"learn":[3.606292637],"iteration":652,"passed_time":1.015280774,"remaining_time":0.5395136731},
{"learn":[3.602753838],"iteration":653,"passed_time":1.016835497,"remaining_time":0.5379588408},
{"learn":[3.599755869],"iteration":654,"passed_time":1.0180973,"remaining_time":0.5362497228},
{"learn":[3.599509575],"iteration":655,"passed_time":1.019307232,"remaining_time":0.534514768},
{"learn":[3.595337722],"iteration":656,"passed_time":1.020647007,"remaining_time":0.5328491983},
{"learn":[3.595168561],"iteration":657,"passed_time":1.021866429,"remaining_time":0.531122065},
{"learn":[3.59290559],"iteration":658,"passed_time":1.023060347,"remaining_time":0.5293832752},
{"learn":[3.592015928],"iteration":659,"passed_time":1.024272234,"remaining_time":0.527655393},
{"learn":[3.590680403],"iteration":660,"passed_time":1.02559353,"remaining_time":0.5259851839},
{"learn":[3.590361532],"iteration":661,"passed_time":1.026878034,"remaining_time":0.5242972437},
{"learn":[3.589069739],"iteration":662,"passed_time":1.028073906,"remaining_time":0.5225654695},
{"learn":[3.585010186],"iteration":663,"passed_time":1.029625808,"remaining_time":0.5210154691},
{"learn":[3.582997552],"iteration":664,"passed_time":1.031003238,"remaining_time":0.5193775708},
{"learn":[3.582119256],"iteration":665,"passed_time":1.032275439,"remaining_time":0.5176876825},
{"learn":[3.579019356],"iteration":666,"passed_time":1.033641665,"remaining_time":0.5160459885},
{"learn":[3.57719559],"iteration":667,"passed_time":1.034939466,"remaining_time":0.5143711117},
{"learn":[3.574050046],"iteration":668,"passed_time":1.03616888,"remaining_time":0.5126635264},
{"learn":[3.572204518],"iteration":669,"passed_time":1.037384775,"remaining_time":0.5109507098},
{"learn":[3.569508025],"iteration":670,"passed_time":1.038750462,"remaining_time":0.5093128196},
{"learn":[3.566268704],"iteration":671,"passed_time":1.039984075,"remaining_time":0.5076112745},
{"learn":[3.562564052],"iteration":672,"passed_time":1.041321164,"remaining_time":0.5059613978},
{"learn":[3.561173586],"iteration":673,"passed_time":1.042640666,"remaining_time":0.5043039421},
{"learn":[3.559551904],"iteration":674,"passed_time":1.04408651,"remaining_time":0.5027083196},
{"learn":[3.558593054],"iteration":675,"passed_time":1.045535865,"remaining_time":0.5011148227},
{"learn":[3.555647008],"iteration":676,"passed_time":1.047099197,"remaining_time":0.499576131},
{"learn":[3.553100059],"iteration":677,"passed_time":1.04830487,"remaining_time":0.4978675048},
{"learn":[3.55085578],"iteration":678,"passed_time":1.049720711,"remaining_time":0.4962597174},
{"learn":[3.550737965],"iteration":679,"passed_time":1.050893514,"remaining_time":0.4945381241},
{"learn":[3.549408772],"iteration":680,"passed_time":1.052172804,"remaining_time":0.4928680242},
{"learn":[3.547390589],"iteration":681,"passed_time":1.053353083,"remaining_time":0.4911529038},
{"learn":[3.54723575],"iteration":682,"passed_time":1.05450895,"remaining_time":0.4894280191},
{"learn":[3.543988891],"iteration":683,"passed_time":1.055676451,"remaining_time":0.4877101735},
{"learn":[3.543868508],"iteration":684,"passed_time":1.056801022,"remaining_time":0.4859741924},
{"learn":[3.542752124],"iteration":685,"passed_time":1.057965211,"remaining_time":0.4842581288},
{"learn":[3.541334315],"iteration":686,"passed_time":1.059362328,"remaining_time":0.4826497942},
{"learn":[3.540208266],"iteration":687,"passed_time":1.060628326,"remaining_time":0.4809826129},
{"learn":[3.537730983],"iteration":688,"passed_time":1.062055383,"remaining_time":0.4793892947},
{"learn":[3.53419867],"iteration":689,"passed_time":1.063201499,"remaining_time":0.4776702386},
{"learn":[3.532628335],"iteration":690,"passed_time":1.064536422,"remaining_time":0.4760372711},
{"learn":[3.532204987],"iteration":691,"passed_time":1.065770194,"remaining_time":0.474360144},
{"learn":[3.530618147],"iteration":692,"passed_time":1.067030094,"remaining_time":0.4726958713},
{"learn":[3.528909306],"iteration":693,"passed_time":1.068396009,"remaining_time":0.4710795083},
{"learn":[3.526700678],"iteration":694,"passed_time":1.069712264,"remaining_time":0.4694420728},
{"learn":[3.526439574],"iteration":695,"passed_time":1.070827264,"remaining_time":0.4677176555},
{"learn":[3.525784216],"iteration":696,"passed_time":1.072133631,"remaining_time":0.466078178},
{"learn":[3.524112693],"iteration":697,"passed_time":1.073402813,"remaining_time":0.4644235667},
{"learn":[3.522813541],"iteration":698,"passed_time":1.074767897,"remaining_time":0.4628113546},
{"learn":[3.519148203],"iteration":699,"passed_time":1.076215422,"remaining_time":0.4612351808},
{"learn":[3.517236747],"iteration":700,"passed_time":1.077476263,"remaining_time":0.4595797469},
{"learn":[3.515603888],"iteration":701,"passed_time":1.078816477,"remaining_time":0.4579591313},
{"learn":[3.51263524],"iteration":702,"passed_time":1.080103955,"remaining_time":0.4563170335},
{"learn":[3.51123442],"iteration":703,"passed_time":1.081513851,"remaining_time":0.4547274147},
{"learn":[3.50828027],"iteration":704,"passed_time":1.082880618,"remaining_time":0.4531202587},
{"learn":[3.508265537],"iteration":705,"passed_time":1.083745833,"remaining_time":0.4513049221},
{"learn":[3.506774876],"iteration":706,"passed_time":1.085124641,"remaining_time":0.4497051201},
{"learn":[3.50552068],"iteration":707,"passed_time":1.086414824,"remaining_time":0.4480693905},
{"learn":[3.501973993],"iteration":708,"passed_time":1.087714237,"remaining_time":0.4464384244},
{"learn":[3.498880354],"iteration":709,"passed_time":1.089131788,"remaining_time":0.4448566459},
{"learn":[3.497370959],"iteration":710,"passed_time":1.090368478,"remaining_time":0.4432018143},
{"learn":[3.496050455],"iteration":711,"passed_time":1.091872583,"remaining_time":0.4416563256},
{"learn":[3.495630067],"iteration":712,"passed_time":1.093159439,"remaining_time":0.440023505},
{"learn":[3.49550669],"iteration":713,"passed_time":1.094352956,"remaining_time":0.4383542655},
{"learn":[3.493652375],"iteration":714,"passed_time":1.095701914,"remaining_time":0.4367483154},
{"learn":[3.491915684],"iteration":715,"passed_time":1.096977754,"remaining_time":0.4351140813},
{"learn":[3.490303956],"iteration":716,"passed_time":1.098269285,"remaining_time":0.4334870398},
{"learn":[3.488363853],"iteration":717,"passed_time":1.099555029,"remaining_time":0.4318586603},
{"learn":[3.485483936],"iteration":718,"passed_time":1.100813922,"remaining_time":0.4302207399},
{"learn":[3.483763466],"iteration":719,"passed_time":1.102091622,"remaining_time":0.4285911865},
{"learn":[3.481642352],"iteration":720,"passed_time":1.103680402,"remaining_time":0.4270829849},
{"learn":[3.479826119],"iteration":721,"passed_time":1.105062292,"remaining_time":0.4254948993},
{"learn":[3.478588728],"iteration":722,"passed_time":1.106601767,"remaining_time":0.4239677584},
{"learn":[3.475390887],"iteration":723,"passed_time":1.108039783,"remaining_time":0.4224019062},
{"learn":[3.472636852],"iteration":724,"passed_time":1.109604892,"remaining_time":0.4208846142},
{"learn":[3.47061883],"iteration":725,"passed_time":1.111127707,"remaining_time":0.4193512283},
{"learn":[3.46953149],"iteration":726,"passed_time":1.112568431,"remaining_time":0.4177870448},
{"learn":[3.467217162],"iteration":727,"passed_time":1.114004686,"remaining_time":0.416221531},
{"learn":[3.465686216],"iteration":728,"passed_time":1.115549639,"remaining_time":0.4146967795},
{"learn":[3.462631216],"iteration":729,"passed_time":1.116809027,"remaining_time":0.4130663525},
{"learn":[3.461451053],"iteration":730,"passed_time":1.118155716,"remaining_time":0.4114690667},
{"learn":[3.458950469],"iteration":731,"passed_time":1.119462574,"remaining_time":0.4098578824},
{"learn":[3.458072145],"iteration":732,"passed_time":1.121506787,"remaining_time":0.4085161148},
{"learn":[3.454364268],"iteration":733,"passed_time":1.1229272,"remaining_time":0.4069463694},
{"learn":[3.453243406],"iteration":734,"passed_time":1.124362222,"remaining_time":0.4053822979},
{"learn":[3.453017963],"iteration":735,"passed_time":1.125736029,"remaining_time":0.4037966192},
{"learn":[3.45201581],"iteration":736,"passed_time":1.126934727,"remaining_time":0.4021490276},
{"learn":[3.449510107],"iteration":737,"passed_time":1.12816174,"remaining_time":0.4005127045},
{"learn":[3.447189189],"iteration":738,"passed_time":1.129478817,"remaining_time":0.3989092981},
{"learn":[3.446423605],"iteration":739,"passed_time":1.130673427,"remaining_time":0.3972636364},
{"learn":[3.445531987],"iteration":740,"passed_time":1.131874841,"remaining_time":0.3956215705},
{"learn":[3.445328199],"iteration":741,"passed_time":1.133228886,"remaining_time":0.3940337635},
{"learn":[3.443327544],"iteration":742,"passed_time":1.134692368,"remaining_time":0.3924844395},
{"learn":[3.441475798],"iteration":743,"passed_time":1.136203419,"remaining_time":0.390951714},
{"learn":[3.439046501],"iteration":744,"passed_time":1.137673257,"remaining_time":0.3894049403},
{"learn":[3.435899469],"iteration":745,"passed_time":1.138979465,"remaining_time":0.3878026596},
{"learn":[3.433988352],"iteration":746,"passed_time":1.140257903,"remaining_time":0.3861917664},
{"learn":[3.433413263],"iteration":747,"passed_time":1.141603197,"remaining_time":0.3846042856},
{"learn":[3.429944699],"iteration":748,"passed_time":1.142856722,"remaining_time":0.3829866986},
{"learn":[3.429291634],"iteration":749,"passed_time":1.144094564,"remaining_time":0.3813648547},
{"learn":[3.429175603],"iteration":750,"passed_time":1.145536447,"remaining_time":0.379811685},
{"learn":[3.428780323],"iteration":751,"passed_time":1.146806978,"remaining_time":0.3782023011},
{"learn":[3.423893341],"iteration":752,"passed_time":1.148248961,"remaining_time":0.3766500577},
{"learn":[3.421024316],"iteration":753,"passed_time":1.149864925,"remaining_time":0.3751548695},
{"learn":[3.420969872],"iteration":754,"passed_time":1.151112087,"remaining_time":0.3735396839},
{"learn":[3.419544785],"iteration":755,"passed_time":1.152469634,"remaining_time":0.3719610989},
{"learn":[3.417057977],"iteration":756,"passed_time":1.153760389,"remaining_time":0.3703616572},
{"learn":[3.415160245],"iteration":757,"passed_time":1.154977236,"remaining_time":0.3687394342},
{"learn":[3.412854597],"iteration":758,"passed_time":1.156299207,"remaining_time":0.3671516587},
{"learn":[3.410926347],"iteration":759,"passed_time":1.157611618,"remaining_time":0.3655615637},
{"learn":[3.408963843],"iteration":760,"passed_time":1.158973986,"remaining_time":0.3639878878},
{"learn":[3.407629634],"iteration":761,"passed_time":1.160202187,"remaining_time":0.3623728616},
{"learn":[3.404384724],"iteration":762,"passed_time":1.161455442,"remaining_time":0.3607666313},
{"learn":[3.403041656],"iteration":763,"passed_time":1.163024731,"remaining_time":0.3592589483},
{"learn":[3.401101731],"iteration":764,"passed_time":1.164478253,"remaining_time":0.3577155418},
{"learn":[3.400890668],"iteration":765,"passed_time":1.1659534,"remaining_time":0.356178976},
{"learn":[3.399289941],"iteration":766,"passed_time":1.167310004,"remaining_time":0.3546065593},
{"learn":[3.399202366],"iteration":767,"passed_time":1.168642269,"remaining_time":0.353027352},
{"learn":[3.397447845],"iteration":768,"passed_time":1.170099599,"remaining_time":0.3514863555},
{"learn":[3.394655341],"iteration":769,"passed_time":1.171440289,"remaining_time":0.3499107357},
{"learn":[3.393228229],"iteration":770,"passed_time":1.172692161,"remaining_time":0.3483093448},
{"learn":[3.389691197],"iteration":771,"passed_time":1.173965649,"remaining_time":0.3467152434},
{"learn":[3.389626772],"iteration":772,"passed_time":1.17525028,"remaining_time":0.345125244},
{"learn":[3.388480222],"iteration":773,"passed_time":1.176519509,"remaining_time":0.3435315362},
{"learn":[3.388215066],"iteration":774,"passed_time":1.178087936,"remaining_time":0.3420255299},
{"learn":[3.386324358],"iteration":775,"passed_time":1.179561217,"remaining_time":0.3404918976},
{"learn":[3.383913061],"iteration":776,"passed_time":1.180975106,"remaining_time":0.3389413752},
{"learn":[3.382839768],"iteration":777,"passed_time":1.182503115,"remaining_time":0.3374237681},
{"learn":[3.381961844],"iteration":778,"passed_time":1.183848187,"remaining_time":0.3358542354},
{"learn":[3.381521703],"iteration":779,"passed_time":1.185057939,"remaining_time":0.3342471111},
{"learn":[3.380918963],"iteration":780,"passed_time":1.186312054,"remaining_time":0.3326534442},
{"learn":[3.377139006],"iteration":781,"passed_time":1.187529583,"remaining_time":0.3310504464},
{"learn":[3.376004372],"iteration":782,"passed_time":1.188799384,"remaining_time":0.32946292},
{"learn":[3.373826468],"iteration":783,"passed_time":1.190119065,"remaining_time":0.3278899464},
{"learn":[3.373546786],"iteration":784,"passed_time":1.191547042,"remaining_time":0.3263472791},
{"learn":[3.372109181],"iteration":785,"passed_time":1.192931092,"remaining_time":0.3247929437},
{"learn":[3.370764924],"iteration":786,"passed_time":1.194408273,"remaining_time":0.3232642468},
{"learn":[3.367833107],"iteration":787,"passed_time":1.195782506,"remaining_time":0.3217079839},
{"learn":[3.36450404],"iteration":788,"passed_time":1.197343618,"remaining_time":0.320202159},
{"learn":[3.361794558],"iteration":789,"passed_time":1.198628991,"remaining_time":0.3186228964},
{"learn":[3.356880529],"iteration":790,"passed_time":1.199882958,"remaining_time":0.3170360786},
{"learn":[3.353843509],"iteration":791,"passed_time":1.201175336,"remaining_time":0.3154601892},
{"learn":[3.353640253],"iteration":792,"passed_time":1.202510801,"remaining_time":0.3138962621},
{"learn":[3.353055088],"iteration":793,"passed_time":1.203833693,"remaining_time":0.3123296484},
{"learn":[3.351415617],"iteration":794,"passed_time":1.205171967,"remaining_time":0.3107676141},
{"learn":[3.349169061],"iteration":795,"passed_time":1.206584495,"remaining_time":0.3092251722},
{"learn":[3.346211014],"iteration":796,"passed_time":1.208096663,"remaining_time":0.3077084348},
{"learn":[3.344560452],"iteration":797,"passed_time":1.209551107,"remaining_time":0.3061770972},
{"learn":[3.344445461],"iteration":798,"passed_time":1.210858242,"remaining_time":0.3046088945},
{"learn":[3.342608898],"iteration":799,"passed_time":1.212215788,"remaining_time":0.3030539471},
{"learn":[3.339572899],"iteration":800,"passed_time":1.213498601,"remaining_time":0.3014809259},
{"learn":[3.339309302],"iteration":801,"passed_time":1.214660882,"remaining_time":0.2998788711},
{"learn":[3.33698088],"iteration":802,"passed_time":1.215947444,"remaining_time":0.2983084015},
{"learn":[3.334746342],"iteration":803,"passed_time":1.217194243,"remaining_time":0.2967289449},
{"learn":[3.332048511],"iteration":804,"passed_time":1.218523003,"remaining_time":0.2951701685},
{"learn":[3.331932544],"iteration":805,"passed_time":1.219847678,"remaining_time":0.2936109795},
{"learn":[3.330541133],"iteration":806,"passed_time":1.221248421,"remaining_time":0.2920705642},
{"learn":[3.329124989],"iteration":807,"passed_time":1.222556834,"remaining_time":0.2905085545},
{"learn":[3.32583918],"iteration":808,"passed_time":1.223776917,"remaining_time":0.288926318},
{"learn":[3.325287299],"iteration":809,"passed_time":1.22510415,"remaining_time":0.2873701093},
{"learn":[3.322745162],"iteration":810,"passed_time":1.226711579,"remaining_time":0.2858797639},
{"learn":[3.319733662],"iteration":811,"passed_time":1.228052068,"remaining_time":0.284327326},
{"learn":[3.318080007],"iteration":812,"passed_time":1.229330388,"remaining_time":0.2827611103},
{"learn":[3.317179538],"iteration":813,"passed_time":1.230696291,"remaining_time":0.2812156144},
{"learn":[3.315685949],"iteration":814,"passed_time":1.231947841,"remaining_time":0.2796446019},
{"learn":[3.314944576],"iteration":815,"passed_time":1.233224349,"remaining_time":0.2780800003},
{"learn":[3.312369052],"iteration":816,"passed_time":1.234712807,"remaining_time":0.2765635785},
{"learn":[3.312321621],"iteration":817,"passed_time":1.235795827,"remaining_time":0.2749570177},
{"learn":[3.309465776],"iteration":818,"passed_time":1.237156206,"remaining_time":0.2734130322},
{"learn":[3.308307377],"iteration":819,"passed_time":1.238526216,"remaining_time":0.2718716083},
{"learn":[3.308076804],"iteration":820,"passed_time":1.239885245,"remaining_time":0.270328208},
{"learn":[3.305643326],"iteration":821,"passed_time":1.241251707,"remaining_time":0.268786866},
{"learn":[3.304154814],"iteration":822,"passed_time":1.242495742,"remaining_time":0.2672196189},
{"learn":[3.303076321],"iteration":823,"passed_time":1.243812594,"remaining_time":0.2656687094},
{"learn":[3.301746372],"iteration":824,"passed_time":1.245153786,"remaining_time":0.2641235304},
{"learn":[3.301345455],"iteration":825,"passed_time":1.246557104,"remaining_time":0.2625919323},
{"learn":[3.299181039],"iteration":826,"passed_time":1.248006273,"remaining_time":0.261070236},
{"learn":[3.297989357],"iteration":827,"passed_time":1.249394179,"remaining_time":0.2595359888},
{"learn":[3.294775182],"iteration":828,"passed_time":1.250822855,"remaining_time":0.2580105045},
{"learn":[3.293840636],"iteration":829,"passed_time":1.252165072,"remaining_time":0.2564675449},
{"learn":[3.289279397],"iteration":830,"passed_time":1.253537932,"remaining_time":0.2549313003},
{"learn":[3.286204979],"iteration":831,"passed_time":1.254892855,"remaining_time":0.2533918266},
{"learn":[3.284833593],"iteration":832,"passed_time":1.256249028,"remaining_time":0.2518530465},
{"learn":[3.283519914],"iteration":833,"passed_time":1.257565869,"remaining_time":0.2503068756},
{"learn":[3.282853026],"iteration":834,"passed_time":1.258880454,"remaining_time":0.2487608084},
{"learn":[3.281944673],"iteration":835,"passed_time":1.260196393,"remaining_time":0.2472155603},
{"learn":[3.279764865],"iteration":836,"passed_time":1.261438385,"remaining_time":0.2456564597},
{"learn":[3.277468839],"iteration":837,"passed_time":1.262924126,"remaining_time":0.2441452367},
{"learn":[3.277124974],"iteration":838,"passed_time":1.26421173,"remaining_time":0.242596053},
{"learn":[3.275636037],"iteration":839,"passed_time":1.265562156,"remaining_time":0.2410594583},
{"learn":[3.274413635],"iteration":840,"passed_time":1.266875788,"remaining_time":0.2395163499},
{"learn":[3.272636087],"iteration":841,"passed_time":1.268369376,"remaining_time":0.2380075551},
{"learn":[3.269644466],"iteration":842,"passed_time":1.26968732,"remaining_time":0.2364660845},
{"learn":[3.26852083],"iteration":843,"passed_time":1.271127319,"remaining_time":0.2349477035},
{"learn":[3.267820927],"iteration":844,"passed_time":1.27255579,"remaining_time":0.2334273935},
{"learn":[3.267331099],"iteration":845,"passed_time":1.273919531,"remaining_time":0.2318955174},
{"learn":[3.267231014],"iteration":846,"passed_time":1.275204844,"remaining_time":0.2303498715},
{"learn":[3.267158695],"iteration":847,"passed_time":1.276428266,"remaining_time":0.2287937459},
{"learn":[3.264718705],"iteration":848,"passed_time":1.277715183,"remaining_time":0.2272496968},
{"learn":[3.261678512],"iteration":849,"passed_time":1.278991136,"remaining_time":0.2257043181},
{"learn":[3.261368381],"iteration":850,"passed_time":1.28032819,"remaining_time":0.2241702706},
{"learn":[3.260128799],"iteration":851,"passed_time":1.281588378,"remaining_time":0.2226233332},
{"learn":[3.258972952],"iteration":852,"passed_time":1.282861124,"remaining_time":0.2210792324},
{"learn":[3.258724846],"iteration":853,"passed_time":1.284239287,"remaining_time":0.2195537891},
{"learn":[3.25686724],"iteration":854,"passed_time":1.285697515,"remaining_time":0.2180422686},
{"learn":[3.255750259],"iteration":855,"passed_time":1.287106141,"remaining_time":0.2165225284},
{"learn":[3.254915866],"iteration":856,"passed_time":1.288421843,"remaining_time":0.2149875421},
{"learn":[3.254348625],"iteration":857,"passed_time":1.289694219,"remaining_time":0.2134458963},
{"learn":[3.253408514],"iteration":858,"passed_time":1.291120968,"remaining_time":0.2119302172},
{"learn":[3.253291714],"iteration":859,"passed_time":1.292387982,"remaining_time":0.2103887413},
{"learn":[3.250186342],"iteration":860,"passed_time":1.293739232,"remaining_time":0.208861502},
{"learn":[3.249141318],"iteration":861,"passed_time":1.2949238,"remaining_time":0.2073079865},
{"learn":[3.246300388],"iteration":862,"passed_time":1.296249685,"remaining_time":0.20577776},
{"learn":[3.245205135],"iteration":863,"passed_time":1.297476704,"remaining_time":0.2042324442},
{"learn":[3.244403535],"iteration":864,"passed_time":1.299046263,"remaining_time":0.2027413242},
{"learn":[3.244211781],"iteration":865,"passed_time":1.300378371,"remaining_time":0.2012132814},
{"learn":[3.242286347],"iteration":866,"passed_time":1.301656044,"remaining_time":0.19967734},
{"learn":[3.239606746],"iteration":867,"passed_time":1.302907885,"remaining_time":0.1981380655},
{"learn":[3.236773361],"iteration":868,"passed_time":1.304225538,"remaining_time":0.1966093733},
{"learn":[3.234552446],"iteration":869,"passed_time":1.305791158,"remaining_time":0.195118219},
{"learn":[3.233724647],"iteration":870,"passed_time":1.307153967,"remaining_time":0.1935968563},
{"learn":[3.230851485],"iteration":871,"passed_time":1.308341462,"remaining_time":0.1920501228},
{"learn":[3.227728941],"iteration":872,"passed_time":1.309636285,"remaining_time":0.1905198261},
{"learn":[3.225787575],"iteration":873,"passed_time":1.310907788,"remaining_time":0.1889867062},
{"learn":[3.222797487],"iteration":874,"passed_time":1.312230632,"remaining_time":0.1874615189},
{"learn":[3.22137014],"iteration":875,"passed_time":1.313742402,"remaining_time":0.1859635364},
{"learn":[3.219701963],"iteration":876,"passed_time":1.315210071,"remaining_time":0.1844593372},
{"learn":[3.21783327],"iteration":877,"passed_time":1.316817756,"remaining_time":0.1829746768},
{"learn":[3.217713355],"iteration":878,"passed_time":1.318116313,"remaining_time":0.1814471831},
{"learn":[3.217666091],"iteration":879,"passed_time":1.319679269,"remaining_time":0.179956264},
{"learn":[3.214962005],"iteration":880,"passed_time":1.320989535,"remaining_time":0.1784310496},
{"learn":[3.214081828],"iteration":881,"passed_time":1.322486078,"remaining_time":0.176931244},
{"learn":[3.213358337],"iteration":882,"passed_time":1.323997876,"remaining_time":0.1754334671},
{"learn":[3.210850401],"iteration":883,"passed_time":1.325309645,"remaining_time":0.1739094105},
{"learn":[3.207810328],"iteration":884,"passed_time":1.326582097,"remaining_time":0.1723807245},
{"learn":[3.204935073],"iteration":885,"passed_time":1.328007203,"remaining_time":0.1708722586},
{"learn":[3.20280198],"iteration":886,"passed_time":1.329353511,"remaining_time":0.1693539422},
{"learn":[3.200663495],"iteration":887,"passed_time":1.33069597,"remaining_time":0.1678355277},
{"learn":[3.197301669],"iteration":888,"passed_time":1.332214386,"remaining_time":0.166339479},
{"learn":[3.195666943],"iteration":889,"passed_time":1.333536937,"remaining_time":0.164819172},
{"learn":[3.193886506],"iteration":890,"passed_time":1.334839637,"remaining_time":0.1632968804},
{"learn":[3.190601248],"iteration":891,"passed_time":1.33614778,"remaining_time":0.1617757402},
{"learn":[3.188983797],"iteration":892,"passed_time":1.337438485,"remaining_time":0.1602529875},
{"learn":[3.187365749],"iteration":893,"passed_time":1.338892242,"remaining_time":0.1587500869},
{"learn":[3.186160771],"iteration":894,"passed_time":1.340300371,"remaining_time":0.157241943},
{"learn":[3.185358981],"iteration":895,"passed_time":1.341667225,"remaining_time":0.1557292314},
{"learn":[3.183832164],"iteration":896,"passed_time":1.34321882,"remaining_time":0.1542380585},
{"learn":[3.183106966],"iteration":897,"passed_time":1.34470417,"remaining_time":0.1527392264},
{"learn":[3.182838152],"iteration":898,"passed_time":1.346100737,"remaining_time":0.1512304498},
{"learn":[3.180835453],"iteration":899,"passed_time":1.347530442,"remaining_time":0.1497256046},
{"learn":[3.179957348],"iteration":900,"passed_time":1.348739723,"remaining_time":0.1481967065},
{"learn":[3.179752966],"iteration":901,"passed_time":1.35004772,"remaining_time":0.1466792423},
{"learn":[3.178851983],"iteration":902,"passed_time":1.351429529,"remaining_time":0.1451701709},
{"learn":[3.176748586],"iteration":903,"passed_time":1.352790805,"remaining_time":0.1436592005},
{"learn":[3.172960988],"iteration":904,"passed_time":1.354458124,"remaining_time":0.1421806871},
{"learn":[3.172794225],"iteration":905,"passed_time":1.355779448,"remaining_time":0.1406658589},
{"learn":[3.169996507],"iteration":906,"passed_time":1.357138043,"remaining_time":0.1391552789},
{"learn":[3.16813015],"iteration":907,"passed_time":1.358812761,"remaining_time":0.1376770639},
{"learn":[3.166920871],"iteration":908,"passed_time":1.360195834,"remaining_time":0.1361692199},
{"learn":[3.16531606],"iteration":909,"passed_time":1.361713509,"remaining_time":0.1346749624},
{"learn":[3.162035247],"iteration":910,"passed_time":1.362935387,"remaining_time":0.1331517557},
{"learn":[3.16189467],"iteration":911,"passed_time":1.36413715,"remaining_time":0.1316272689},
{"learn":[3.161008416],"iteration":912,"passed_time":1.365410287,"remaining_time":0.1301102902},
{"learn":[3.160560787],"iteration":913,"passed_time":1.366616044,"remaining_time":0.1285875053},
{"learn":[3.160416261],"iteration":914,"passed_time":1.367996091,"remaining_time":0.1270816041},
{"learn":[3.15844291],"iteration":915,"passed_time":1.369502963,"remaining_time":0.125587608},
{"learn":[3.155040501],"iteration":916,"passed_time":1.371023883,"remaining_time":0.1240948553},
{"learn":[3.154937548],"iteration":917,"passed_time":1.372300174,"remaining_time":0.1225801899},
{"learn":[3.153721161],"iteration":918,"passed_time":1.373719266,"remaining_time":0.1210786295},
{"learn":[3.153170511],"iteration":919,"passed_time":1.375096953,"remaining_time":0.1195736481},
{"learn":[3.153113601],"iteration":920,"passed_time":1.376486934,"remaining_time":0.1180699976},
{"learn":[3.150607379],"iteration":921,"passed_time":1.377828888,"remaining_time":0.1165625306},
{"learn":[3.148408359],"iteration":922,"passed_time":1.379207629,"remaining_time":0.1150584912},
{"learn":[3.147495728],"iteration":923,"passed_time":1.380623487,"remaining_time":0.113557776},
{"learn":[3.146946235],"iteration":924,"passed_time":1.381921602,"remaining_time":0.1120476975},
{"learn":[3.14472738],"iteration":925,"passed_time":1.383226602,"remaining_time":0.110538627},
{"learn":[3.144469477],"iteration":926,"passed_time":1.384420735,"remaining_time":0.1090212661},
{"learn":[3.142975516],"iteration":927,"passed_time":1.385633403,"remaining_time":0.1075060399},
{"learn":[3.14079113],"iteration":928,"passed_time":1.386902862,"remaining_time":0.1059958054},
{"learn":[3.138173032],"iteration":929,"passed_time":1.388318665,"remaining_time":0.1044971038},
{"learn":[3.136352813],"iteration":930,"passed_time":1.389824695,"remaining_time":0.1030052674},
{"learn":[3.133735004],"iteration":931,"passed_time":1.391775408,"remaining_time":0.1015458453},
{"learn":[3.1319496],"iteration":932,"passed_time":1.393095796,"remaining_time":0.1000401054},
{"learn":[3.129865343],"iteration":933,"passed_time":1.394600731,"remaining_time":0.09854780325},
{"learn":[3.129830206],"iteration":934,"passed_time":1.395626586,"remaining_time":0.09702216911},
{"learn":[3.126676562],"iteration":935,"passed_time":1.396896368,"remaining_time":0.09551428155},
{"learn":[3.12645665],"iteration":936,"passed_time":1.398216194,"remaining_time":0.09401026707},
{"learn":[3.126378007],"iteration":937,"passed_time":1.399473027,"remaining_time":0.09250248151},
{"learn":[3.124621914],"iteration":938,"passed_time":1.400777884,"remaining_time":0.09099835031},
{"learn":[3.123379018],"iteration":939,"passed_time":1.402085184,"remaining_time":0.089494799},
{"learn":[3.123332451],"iteration":940,"passed_time":1.403531198,"remaining_time":0.08800036203},
{"learn":[3.122432444],"iteration":941,"passed_time":1.404934201,"remaining_time":0.08650337966},
{"learn":[3.121889006],"iteration":942,"passed_time":1.406376624,"remaining_time":0.08500897942},
{"learn":[3.121070914],"iteration":943,"passed_time":1.407775729,"remaining_time":0.08351211952},
{"learn":[3.118444705],"iteration":944,"passed_time":1.409348717,"remaining_time":0.08202558673},
{"learn":[3.116820458],"iteration":945,"passed_time":1.410669847,"remaining_time":0.08052449444},
{"learn":[3.114971041],"iteration":946,"passed_time":1.411909453,"remaining_time":0.07901921963},
{"learn":[3.114685138],"iteration":947,"passed_time":1.413139488,"remaining_time":0.07751398034},
{"learn":[3.113399363],"iteration":948,"passed_time":1.414498954,"remaining_time":0.07601627676},
{"learn":[3.110575399],"iteration":949,"passed_time":1.415823967,"remaining_time":0.07451705089},
{"learn":[3.110466553],"iteration":950,"passed_time":1.417061454,"remaining_time":0.07301368165},
{"learn":[3.108691641],"iteration":951,"passed_time":1.418450749,"remaining_time":0.07151852517},
{"learn":[3.107898017],"iteration":952,"passed_time":1.419895716,"remaining_time":0.07002633645},
{"learn":[3.105551729],"iteration":953,"passed_time":1.421451257,"remaining_time":0.06853957842},
{"learn":[3.104824945],"iteration":954,"passed_time":1.422821106,"remaining_time":0.06704392648},
{"learn":[3.103186704],"iteration":955,"passed_time":1.424174006,"remaining_time":0.06554775762},
{"learn":[3.102330655],"iteration":956,"passed_time":1.425495183,"remaining_time":0.06405046279},
{"learn":[3.102291298],"iteration":957,"passed_time":1.42680601,"remaining_time":0.06255308185},
{"learn":[3.100363529],"iteration":958,"passed_time":1.428217918,"remaining_time":0.06106041152},
{"learn":[3.097871596],"iteration":959,"passed_time":1.429481295,"remaining_time":0.05956172061},
{"learn":[3.097372213],"iteration":960,"passed_time":1.43090613,"remaining_time":0.05807007188},
{"learn":[3.095981813],"iteration":961,"passed_time":1.43216008,"remaining_time":0.0565718119},
{"learn":[3.095347452],"iteration":962,"passed_time":1.433578454,"remaining_time":0.05508037672},
{"learn":[3.094728409],"iteration":963,"passed_time":1.435199609,"remaining_time":0.05359666588},
{"learn":[3.094118537],"iteration":964,"passed_time":1.436540044,"remaining_time":0.05210248865},
{"learn":[3.093793695],"iteration":965,"passed_time":1.437844702,"remaining_time":0.05060737048},
{"learn":[3.092581602],"iteration":966,"passed_time":1.439165653,"remaining_time":0.04911320222},
{"learn":[3.091694202],"iteration":967,"passed_time":1.440494544,"remaining_time":0.04761965434},
{"learn":[3.090298312],"iteration":968,"passed_time":1.441875952,"remaining_time":0.04612812643},
{"learn":[3.090020107],"iteration":969,"passed_time":1.443253817,"remaining_time":0.04463671598},
{"learn":[3.088949869],"iteration":970,"passed_time":1.444625911,"remaining_time":0.04314536707},
{"learn":[3.086700204],"iteration":971,"passed_time":1.445809237,"remaining_time":0.04164882574},
{"learn":[3.086584317],"iteration":972,"passed_time":1.447151456,"remaining_time":0.04015733743},
{"learn":[3.084850742],"iteration":973,"passed_time":1.448525866,"remaining_time":0.0386670149},
{"learn":[3.084239948],"iteration":974,"passed_time":1.450007261,"remaining_time":0.03717967336},
{"learn":[3.082561673],"iteration":975,"passed_time":1.451441743,"remaining_time":0.03569119039},
{"learn":[3.07991814],"iteration":976,"passed_time":1.453451839,"remaining_time":0.03421636877},
{"learn":[3.079350277],"iteration":977,"passed_time":1.45499668,"remaining_time":0.03272998666},
{"learn":[3.077637462],"iteration":978,"passed_time":1.45654699,"remaining_time":0.03124360243},
{"learn":[3.076733301],"iteration":979,"passed_time":1.458127612,"remaining_time":0.02975770636},
{"learn":[3.07594065],"iteration":980,"passed_time":1.459474303,"remaining_time":0.0282670864},
{"learn":[3.072594655],"iteration":981,"passed_time":1.461020563,"remaining_time":0.02678041766},
{"learn":[3.071977674],"iteration":982,"passed_time":1.462533839,"remaining_time":0.02529305724},
{"learn":[3.069532634],"iteration":983,"passed_time":1.464554465,"remaining_time":0.02381389375},
{"learn":[3.068870784],"iteration":984,"passed_time":1.466100864,"remaining_time":0.0223264091},
{"learn":[3.068801463],"iteration":985,"passed_time":1.467529339,"remaining_time":0.02083713058},
{"learn":[3.067433249],"iteration":986,"passed_time":1.469019545,"remaining_time":0.01934878833},
{"learn":[3.065611456],"iteration":987,"passed_time":1.470773037,"remaining_time":0.01786364013},
{"learn":[3.063039162],"iteration":988,"passed_time":1.472206084,"remaining_time":0.01637438516},
{"learn":[3.06177873],"iteration":989,"passed_time":1.473939425,"remaining_time":0.01488827702},
{"learn":[3.061689148],"iteration":990,"passed_time":1.475345225,"remaining_time":0.01339869528},
{"learn":[3.058984039],"iteration":991,"passed_time":1.47690646,"remaining_time":0.01191053597},
{"learn":[3.057492984],"iteration":992,"passed_time":1.478540934,"remaining_time":0.01042274576},
{"learn":[3.057290731],"iteration":993,"passed_time":1.479991851,"remaining_time":0.008933552418},
{"learn":[3.056068348],"iteration":994,"passed_time":1.481375223,"remaining_time":0.007444096598},
{"learn":[3.054987307],"iteration":995,"passed_time":1.482868079,"remaining_time":0.00595529349},
{"learn":[3.054200234],"iteration":996,"passed_time":1.484427541,"remaining_time":0.004466682672},
{"learn":[3.052732869],"iteration":997,"passed_time":1.485929938,"remaining_time":0.002977815506},
{"learn":[3.051787862],"iteration":998,"passed_time":1.487399104,"remaining_time":0.001488887992},
{"learn":[3.051366222],"iteration":999,"passed_time":1.488920451,"remaining_time":0}
]}